{"directed": false, "multigraph": false, "graph": {}, "nodes": [{"gender": "f", "nationality": "Czech Republic", "year": 2003.0, "centrality_measures": {"degree_centrality": 0.057777777777777775, "closeness_centrality": 0.05807407407407408, "betweenness_centrality": 0.00014550264550264547, "eigenvector_centrality": 0.27991980238631176, "pagerank": 0.010536118773807331, "clustering_coefficient": 0.8717948717948718}, "id": "Adela Babanova"}, {"gender": "f", "nationality": "Germany", "year": 2003.0, "centrality_measures": {"degree_centrality": 0.0, "closeness_centrality": 0.0, "betweenness_centrality": 0.0, "eigenvector_centrality": 5.5724414651128046e-27, "pagerank": 0.0013591987194371152, "clustering_coefficient": 0}, "id": "Martina Munse"}, {"gender": "f", "nationality": NaN, "year": 2003.0, "centrality_measures": {"degree_centrality": 0.05333333333333333, "closeness_centrality": 0.05444444444444444, "betweenness_centrality": 0.0, "eigenvector_centrality": 0.27460817448713837, "pagerank": 0.009576056929916374, "clustering_coefficient": 1.0}, "id": "Linda Ciharov\u00ef\u00bf\u00bd"}, {"gender": "m", "nationality": "Bosnia and Herzegovina", "year": 2003.0, "centrality_measures": {"degree_centrality": 0.0, "closeness_centrality": 0.0, "betweenness_centrality": 0.0, "eigenvector_centrality": 5.5724414651128046e-27, "pagerank": 0.0013591987194371152, "clustering_coefficient": 0}, "id": "Jasko Begovic"}, {"gender": "f", "nationality": "Slovakia", "year": 2003.0, "centrality_measures": {"degree_centrality": 0.0, "closeness_centrality": 0.0, "betweenness_centrality": 0.0, "eigenvector_centrality": 5.5724414651128046e-27, "pagerank": 0.0013591987194371152, "clustering_coefficient": 0}, "id": "Daniela Krajcova"}, {"gender": "m", "nationality": "Slovakia", "year": 2003.0, "centrality_measures": {"degree_centrality": 0.0, "closeness_centrality": 0.0, "betweenness_centrality": 0.0, "eigenvector_centrality": 5.5724414651128046e-27, "pagerank": 0.0013591987194371152, "clustering_coefficient": 0}, "id": "Michal Czinege"}, {"gender": "f", "nationality": "USA", "year": 2003.0, "centrality_measures": {"degree_centrality": 0.0, "closeness_centrality": 0.0, "betweenness_centrality": 0.0, "eigenvector_centrality": 5.5724414651128046e-27, "pagerank": 0.0013591987194371152, "clustering_coefficient": 0}, "id": "Lindsey White"}, {"gender": "m", "nationality": "Mexico", "year": 2003.0, "centrality_measures": {"degree_centrality": 0.0, "closeness_centrality": 0.0, "betweenness_centrality": 0.0, "eigenvector_centrality": 5.5724414651128046e-27, "pagerank": 0.0013591987194371152, "clustering_coefficient": 0}, "id": "Erick Meyenberg"}, {"gender": "f", "nationality": NaN, "year": 2003.0, "centrality_measures": {"degree_centrality": 0.0, "closeness_centrality": 0.0, "betweenness_centrality": 0.0, "eigenvector_centrality": 5.5724414651128046e-27, "pagerank": 0.0013591987194371152, "clustering_coefficient": 0}, "id": "Anna Kristensen"}, {"gender": "f", "nationality": "Austria", "year": 2003.0, "centrality_measures": {"degree_centrality": 0.0, "closeness_centrality": 0.0, "betweenness_centrality": 0.0, "eigenvector_centrality": 5.5724414651128046e-27, "pagerank": 0.0013591987194371152, "clustering_coefficient": 0}, "id": "Elisabeth Schmirl"}, {"gender": "m", "nationality": "Austria", "year": 2003.0, "centrality_measures": {"degree_centrality": 0.0, "closeness_centrality": 0.0, "betweenness_centrality": 0.0, "eigenvector_centrality": 5.5724414651128046e-27, "pagerank": 0.0013591987194371152, "clustering_coefficient": 0}, "id": "Georg Eger"}, {"gender": "m", "nationality": "Japan", "year": 2003.0, "centrality_measures": {"degree_centrality": 0.0, "closeness_centrality": 0.0, "betweenness_centrality": 0.0, "eigenvector_centrality": 5.5724414651128046e-27, "pagerank": 0.0013591987194371152, "clustering_coefficient": 0}, "id": "Naoki Yamamoto"}, {"gender": "m", "nationality": "Serbia", "year": 2003.0, "centrality_measures": {"degree_centrality": 0.0, "closeness_centrality": 0.0, "betweenness_centrality": 0.0, "eigenvector_centrality": 5.5724414651128046e-27, "pagerank": 0.0013591987194371152, "clustering_coefficient": 0}, "id": "Ivan Zupanc"}, {"gender": "m", "nationality": "France", "year": 2003.0, "centrality_measures": {"degree_centrality": 0.0, "closeness_centrality": 0.0, "betweenness_centrality": 0.0, "eigenvector_centrality": 5.5724414651128046e-27, "pagerank": 0.0013591987194371152, "clustering_coefficient": 0}, "id": "Vincent Bullat"}, {"gender": "f", "nationality": "Greece", "year": 2003.0, "centrality_measures": {"degree_centrality": 0.0, "closeness_centrality": 0.0, "betweenness_centrality": 0.0, "eigenvector_centrality": 5.5724414651128046e-27, "pagerank": 0.0013591987194371152, "clustering_coefficient": 0}, "id": "Maria-Brigita Karantzi"}, {"gender": "m", "nationality": "United Kingdom", "year": 2003.0, "centrality_measures": {"degree_centrality": 0.0, "closeness_centrality": 0.0, "betweenness_centrality": 0.0, "eigenvector_centrality": 5.5724414651128046e-27, "pagerank": 0.0013591987194371152, "clustering_coefficient": 0}, "id": "Daniel Pasteiner"}, {"gender": "m", "nationality": "Germany", "year": 2003.0, "centrality_measures": {"degree_centrality": 0.0, "closeness_centrality": 0.0, "betweenness_centrality": 0.0, "eigenvector_centrality": 5.5724414651128046e-27, "pagerank": 0.0013591987194371152, "clustering_coefficient": 0}, "id": "Peter Piek"}, {"gender": "m", "nationality": "Slovakia", "year": 2003.0, "centrality_measures": {"degree_centrality": 0.013333333333333332, "closeness_centrality": 0.013333333333333334, "betweenness_centrality": 0.0, "eigenvector_centrality": 3.921257079035301e-13, "pagerank": 0.00905721082396169, "clustering_coefficient": 1.0}, "id": "Radovan Cerevka"}, {"gender": "m", "nationality": "Belgium", "year": 2003.0, "centrality_measures": {"degree_centrality": 0.017777777777777778, "closeness_centrality": 0.017777777777777778, "betweenness_centrality": 0.0, "eigenvector_centrality": 6.64286788119412e-11, "pagerank": 0.00905721082396169, "clustering_coefficient": 1.0}, "id": "Antoine Roegiers"}, {"gender": "m", "nationality": "China", "year": 2003.0, "centrality_measures": {"degree_centrality": 0.0, "closeness_centrality": 0.0, "betweenness_centrality": 0.0, "eigenvector_centrality": 5.5724414651128046e-27, "pagerank": 0.0013591987194371152, "clustering_coefficient": 0}, "id": "Zhang Guo Ning"}, {"gender": "f", "nationality": NaN, "year": 2003.0, "centrality_measures": {"degree_centrality": 0.0, "closeness_centrality": 0.0, "betweenness_centrality": 0.0, "eigenvector_centrality": 5.5724414651128046e-27, "pagerank": 0.0013591987194371152, "clustering_coefficient": 0}, "id": "Ana Bagayan"}, {"gender": "m", "nationality": "China", "year": 2003.0, "centrality_measures": {"degree_centrality": 0.0, "closeness_centrality": 0.0, "betweenness_centrality": 0.0, "eigenvector_centrality": 5.5724414651128046e-27, "pagerank": 0.0013591987194371152, "clustering_coefficient": 0}, "id": "Lei Ming"}, {"gender": "f", "nationality": "Switzerland", "year": 2003.0, "centrality_measures": {"degree_centrality": 0.0, "closeness_centrality": 0.0, "betweenness_centrality": 0.0, "eigenvector_centrality": 5.5724414651128046e-27, "pagerank": 0.0013591987194371152, "clustering_coefficient": 0}, "id": "Nathalie Perrin"}, {"gender": "m", "nationality": "USA", "year": 2003.0, "centrality_measures": {"degree_centrality": 0.0, "closeness_centrality": 0.0, "betweenness_centrality": 0.0, "eigenvector_centrality": 5.5724414651128046e-27, "pagerank": 0.0013591987194371152, "clustering_coefficient": 0}, "id": "Brad Downey"}, {"gender": "m", "nationality": "Australia", "year": 2003.0, "centrality_measures": {"degree_centrality": 0.0, "closeness_centrality": 0.0, "betweenness_centrality": 0.0, "eigenvector_centrality": 5.5724414651128046e-27, "pagerank": 0.0013591987194371152, "clustering_coefficient": 0}, "id": "Sam Smith"}, {"gender": "f", "nationality": "Germany", "year": 2003.0, "centrality_measures": {"degree_centrality": 0.035555555555555556, "closeness_centrality": 0.036000000000000004, "betweenness_centrality": 0.0, "eigenvector_centrality": 5.173563042593662e-05, "pagerank": 0.00956794035321134, "clustering_coefficient": 1.0}, "id": "Sina Heffner"}, {"gender": "f", "nationality": "Germany", "year": 2003.0, "centrality_measures": {"degree_centrality": 0.0, "closeness_centrality": 0.0, "betweenness_centrality": 0.0, "eigenvector_centrality": 5.5724414651128046e-27, "pagerank": 0.0013591987194371152, "clustering_coefficient": 0}, "id": "Ulrike H\u00f6rdler"}, {"gender": "f", "nationality": "Germany", "year": 2003.0, "centrality_measures": {"degree_centrality": 0.0, "closeness_centrality": 0.0, "betweenness_centrality": 0.0, "eigenvector_centrality": 5.5724414651128046e-27, "pagerank": 0.0013591987194371152, "clustering_coefficient": 0}, "id": "Eva Maria Raschpichler"}, {"gender": "m", "nationality": "China", "year": 2003.0, "centrality_measures": {"degree_centrality": 0.0, "closeness_centrality": 0.0, "betweenness_centrality": 0.0, "eigenvector_centrality": 5.5724414651128046e-27, "pagerank": 0.0013591987194371152, "clustering_coefficient": 0}, "id": "Liu Yi"}, {"gender": "f", "nationality": NaN, "year": 2003.0, "centrality_measures": {"degree_centrality": 0.0, "closeness_centrality": 0.0, "betweenness_centrality": 0.0, "eigenvector_centrality": 5.5724414651128046e-27, "pagerank": 0.0013591987194371152, "clustering_coefficient": 0}, "id": "Ginger Wolfe-Suarez"}, {"gender": "f", "nationality": "Austria", "year": 2003.0, "centrality_measures": {"degree_centrality": 0.017777777777777778, "closeness_centrality": 0.017777777777777778, "betweenness_centrality": 0.0, "eigenvector_centrality": 6.64286788119412e-11, "pagerank": 0.00905721082396169, "clustering_coefficient": 1.0}, "id": "Ana Hoffner"}, {"gender": "f", "nationality": "Austria", "year": 2003.0, "centrality_measures": {"degree_centrality": 0.017777777777777778, "closeness_centrality": 0.017777777777777778, "betweenness_centrality": 0.0, "eigenvector_centrality": 6.64286788119412e-11, "pagerank": 0.00905721082396169, "clustering_coefficient": 1.0}, "id": "Anna Barfuss"}, {"gender": "m", "nationality": "Austria", "year": 2003.0, "centrality_measures": {"degree_centrality": 0.017777777777777778, "closeness_centrality": 0.017777777777777778, "betweenness_centrality": 0.0, "eigenvector_centrality": 6.64286788119412e-11, "pagerank": 0.00905721082396169, "clustering_coefficient": 1.0}, "id": "Georg Tiller"}, {"gender": "f", "nationality": "Austria", "year": 2003.0, "centrality_measures": {"degree_centrality": 0.017777777777777778, "closeness_centrality": 0.017777777777777778, "betweenness_centrality": 0.0, "eigenvector_centrality": 6.64286788119412e-11, "pagerank": 0.00905721082396169, "clustering_coefficient": 1.0}, "id": "Verena Dengler"}, {"gender": "f", "nationality": "United Kingdom", "year": 2003.0, "centrality_measures": {"degree_centrality": 0.0, "closeness_centrality": 0.0, "betweenness_centrality": 0.0, "eigenvector_centrality": 5.5724414651128046e-27, "pagerank": 0.0013591987194371152, "clustering_coefficient": 0}, "id": "Sarah Forrest"}, {"gender": "m", "nationality": "China", "year": 2003.0, "centrality_measures": {"degree_centrality": 0.0044444444444444444, "closeness_centrality": 0.0044444444444444444, "betweenness_centrality": 0.0, "eigenvector_centrality": 4.6745027053776994e-20, "pagerank": 0.00905721082396169, "clustering_coefficient": 0}, "id": "Wei Jia"}, {"gender": "m", "nationality": "Germany", "year": 2003.0, "centrality_measures": {"degree_centrality": 0.035555555555555556, "closeness_centrality": 0.036000000000000004, "betweenness_centrality": 0.0, "eigenvector_centrality": 5.173563042593662e-05, "pagerank": 0.00956794035321134, "clustering_coefficient": 1.0}, "id": "Gabriel Braun"}, {"gender": "m", "nationality": "Switzerland", "year": 2003.0, "centrality_measures": {"degree_centrality": 0.0, "closeness_centrality": 0.0, "betweenness_centrality": 0.0, "eigenvector_centrality": 5.5724414651128046e-27, "pagerank": 0.0013591987194371152, "clustering_coefficient": 0}, "id": "Sam Graf"}, {"gender": "m", "nationality": "Albania", "year": 2003.0, "centrality_measures": {"degree_centrality": 0.0, "closeness_centrality": 0.0, "betweenness_centrality": 0.0, "eigenvector_centrality": 5.5724414651128046e-27, "pagerank": 0.0013591987194371152, "clustering_coefficient": 0}, "id": "Armando Lulaj"}, {"gender": "m", "nationality": NaN, "year": 2003.0, "centrality_measures": {"degree_centrality": 0.0, "closeness_centrality": 0.0, "betweenness_centrality": 0.0, "eigenvector_centrality": 5.5724414651128046e-27, "pagerank": 0.0013591987194371152, "clustering_coefficient": 0}, "id": "Benjamin Jones"}, {"gender": "f", "nationality": "USA", "year": 2003.0, "centrality_measures": {"degree_centrality": 0.017777777777777778, "closeness_centrality": 0.017777777777777778, "betweenness_centrality": 0.0, "eigenvector_centrality": 6.64286788119412e-11, "pagerank": 0.00905721082396169, "clustering_coefficient": 1.0}, "id": "Julie Curtiss"}, {"gender": "m", "nationality": "France", "year": 2003.0, "centrality_measures": {"degree_centrality": 0.0, "closeness_centrality": 0.0, "betweenness_centrality": 0.0, "eigenvector_centrality": 5.5724414651128046e-27, "pagerank": 0.0013591987194371152, "clustering_coefficient": 0}, "id": "JR"}, {"gender": "m", "nationality": "USA", "year": 2003.0, "centrality_measures": {"degree_centrality": 0.0, "closeness_centrality": 0.0, "betweenness_centrality": 0.0, "eigenvector_centrality": 5.5724414651128046e-27, "pagerank": 0.0013591987194371152, "clustering_coefficient": 0}, "id": "Kenneth Andrew Mroczek"}, {"gender": "m", "nationality": "Switzerland", "year": 2003.0, "centrality_measures": {"degree_centrality": 0.035555555555555556, "closeness_centrality": 0.036000000000000004, "betweenness_centrality": 0.0, "eigenvector_centrality": 5.173563042593662e-05, "pagerank": 0.00956794035321134, "clustering_coefficient": 1.0}, "id": "Lukas Beyeler"}, {"gender": "m", "nationality": NaN, "year": 2003.0, "centrality_measures": {"degree_centrality": 0.017777777777777778, "closeness_centrality": 0.01851851851851852, "betweenness_centrality": 0.0, "eigenvector_centrality": 8.628033669392661e-11, "pagerank": 0.009597373066347566, "clustering_coefficient": 1.0}, "id": "Joe Grillo"}, {"gender": "f", "nationality": "France", "year": 2003.0, "centrality_measures": {"degree_centrality": 0.017777777777777778, "closeness_centrality": 0.017777777777777778, "betweenness_centrality": 0.0, "eigenvector_centrality": 6.64286788119412e-11, "pagerank": 0.00905721082396169, "clustering_coefficient": 1.0}, "id": "Estelle Hanania"}, {"gender": "m", "nationality": "Italy", "year": 2003.0, "centrality_measures": {"degree_centrality": 0.0044444444444444444, "closeness_centrality": 0.0044444444444444444, "betweenness_centrality": 0.0, "eigenvector_centrality": 4.6745027053776994e-20, "pagerank": 0.00905721082396169, "clustering_coefficient": 0}, "id": "Davide Zucco"}, {"gender": "f", "nationality": "Slovakia", "year": 2003.0, "centrality_measures": {"degree_centrality": 0.0, "closeness_centrality": 0.0, "betweenness_centrality": 0.0, "eigenvector_centrality": 5.5724414651128046e-27, "pagerank": 0.0013591987194371152, "clustering_coefficient": 0}, "id": "Dorota Kenderov\u00e1"}, {"gender": "f", "nationality": "Brazil", "year": 2003.0, "centrality_measures": {"degree_centrality": 0.0, "closeness_centrality": 0.0, "betweenness_centrality": 0.0, "eigenvector_centrality": 5.5724414651128046e-27, "pagerank": 0.0013591987194371152, "clustering_coefficient": 0}, "id": "Aline Van Langendonck"}, {"gender": "m", "nationality": "USA", "year": 2003.0, "centrality_measures": {"degree_centrality": 0.0, "closeness_centrality": 0.0, "betweenness_centrality": 0.0, "eigenvector_centrality": 5.5724414651128046e-27, "pagerank": 0.0013591987194371152, "clustering_coefficient": 0}, "id": "Aaron Koblin"}, {"gender": "f", "nationality": "Germany", "year": 2003.0, "centrality_measures": {"degree_centrality": 0.0, "closeness_centrality": 0.0, "betweenness_centrality": 0.0, "eigenvector_centrality": 5.5724414651128046e-27, "pagerank": 0.0013591987194371152, "clustering_coefficient": 0}, "id": "Ulrike Theusner"}, {"gender": "f", "nationality": "France", "year": 2003.0, "centrality_measures": {"degree_centrality": 0.0, "closeness_centrality": 0.0, "betweenness_centrality": 0.0, "eigenvector_centrality": 5.5724414651128046e-27, "pagerank": 0.0013591987194371152, "clustering_coefficient": 0}, "id": "Julie Faure-Brac"}, {"gender": "f", "nationality": "Austria", "year": 2003.0, "centrality_measures": {"degree_centrality": 0.017777777777777778, "closeness_centrality": 0.017777777777777778, "betweenness_centrality": 0.0, "eigenvector_centrality": 1.8180875376242893e-10, "pagerank": 0.008687999339811495, "clustering_coefficient": 1.0}, "id": "Miriam Laussegger"}, {"gender": "m", "nationality": "Austria", "year": 2003.0, "centrality_measures": {"degree_centrality": 0.026666666666666665, "closeness_centrality": 0.017777777777777778, "betweenness_centrality": 0.0, "eigenvector_centrality": 2.247279785548828e-10, "pagerank": 0.01053405676056246, "clustering_coefficient": 1.0}, "id": "Christoph Meier"}, {"gender": "f", "nationality": "Poland", "year": 2003.0, "centrality_measures": {"degree_centrality": 0.0044444444444444444, "closeness_centrality": 0.0044444444444444444, "betweenness_centrality": 0.0, "eigenvector_centrality": 4.6745027053776994e-20, "pagerank": 0.00905721082396169, "clustering_coefficient": 0}, "id": "Anna Loskiewicz"}, {"gender": "f", "nationality": "Ukraine", "year": 2003.0, "centrality_measures": {"degree_centrality": 0.0, "closeness_centrality": 0.0, "betweenness_centrality": 0.0, "eigenvector_centrality": 5.5724414651128046e-27, "pagerank": 0.0013591987194371152, "clustering_coefficient": 0}, "id": "Lada Nakonechna"}, {"gender": "m", "nationality": "Japan", "year": 2003.0, "centrality_measures": {"degree_centrality": 0.0, "closeness_centrality": 0.0, "betweenness_centrality": 0.0, "eigenvector_centrality": 5.5724414651128046e-27, "pagerank": 0.0013591987194371152, "clustering_coefficient": 0}, "id": "Takeshi Makishima"}, {"gender": "m", "nationality": "Canada", "year": 2003.0, "centrality_measures": {"degree_centrality": 0.0, "closeness_centrality": 0.0, "betweenness_centrality": 0.0, "eigenvector_centrality": 5.5724414651128046e-27, "pagerank": 0.0013591987194371152, "clustering_coefficient": 0}, "id": "Andrew Dadson"}, {"gender": "f", "nationality": "China", "year": 2003.0, "centrality_measures": {"degree_centrality": 0.0, "closeness_centrality": 0.0, "betweenness_centrality": 0.0, "eigenvector_centrality": 5.5724414651128046e-27, "pagerank": 0.0013591987194371152, "clustering_coefficient": 0}, "id": "Han Bing"}, {"gender": "m", "nationality": "United Kingdom", "year": 2003.0, "centrality_measures": {"degree_centrality": 0.0, "closeness_centrality": 0.0, "betweenness_centrality": 0.0, "eigenvector_centrality": 5.5724414651128046e-27, "pagerank": 0.0013591987194371152, "clustering_coefficient": 0}, "id": "Stuart Semple"}, {"gender": "f", "nationality": "Switzerland", "year": 2003.0, "centrality_measures": {"degree_centrality": 0.0, "closeness_centrality": 0.0, "betweenness_centrality": 0.0, "eigenvector_centrality": 5.5724414651128046e-27, "pagerank": 0.0013591987194371152, "clustering_coefficient": 0}, "id": "Regine von Felten"}, {"gender": "m", "nationality": "Canada", "year": 2003.0, "centrality_measures": {"degree_centrality": 0.0, "closeness_centrality": 0.0, "betweenness_centrality": 0.0, "eigenvector_centrality": 5.5724414651128046e-27, "pagerank": 0.0013591987194371152, "clustering_coefficient": 0}, "id": "Kotama Bouabane"}, {"gender": "f", "nationality": "Germany", "year": 2003.0, "centrality_measures": {"degree_centrality": 0.0, "closeness_centrality": 0.0, "betweenness_centrality": 0.0, "eigenvector_centrality": 5.5724414651128046e-27, "pagerank": 0.0013591987194371152, "clustering_coefficient": 0}, "id": "Dorothea Strauss"}, {"gender": "m", "nationality": "USA", "year": 2003.0, "centrality_measures": {"degree_centrality": 0.0, "closeness_centrality": 0.0, "betweenness_centrality": 0.0, "eigenvector_centrality": 5.5724414651128046e-27, "pagerank": 0.0013591987194371152, "clustering_coefficient": 0}, "id": "Chadwick Rantanen"}, {"gender": "f", "nationality": "Switzerland", "year": 2003.0, "centrality_measures": {"degree_centrality": 0.0044444444444444444, "closeness_centrality": 0.0044444444444444444, "betweenness_centrality": 0.0, "eigenvector_centrality": 4.6745027053776994e-20, "pagerank": 0.00905721082396169, "clustering_coefficient": 0}, "id": "Noemi Grieder"}, {"gender": "m", "nationality": "Switzerland", "year": 2003.0, "centrality_measures": {"degree_centrality": 0.0044444444444444444, "closeness_centrality": 0.0044444444444444444, "betweenness_centrality": 0.0, "eigenvector_centrality": 4.6745027053776994e-20, "pagerank": 0.00905721082396169, "clustering_coefficient": 0}, "id": "Tobias Kaspar"}, {"gender": "f", "nationality": NaN, "year": 2003.0, "centrality_measures": {"degree_centrality": 0.008888888888888889, "closeness_centrality": 0.008888888888888889, "betweenness_centrality": 0.0, "eigenvector_centrality": 5.246073533531044e-16, "pagerank": 0.00905721082396169, "clustering_coefficient": 1.0}, "id": "Amy Howden-Chapman"}, {"gender": "m", "nationality": "Australia", "year": 2003.0, "centrality_measures": {"degree_centrality": 0.0044444444444444444, "closeness_centrality": 0.0044444444444444444, "betweenness_centrality": 0.0, "eigenvector_centrality": 4.6745027053776994e-20, "pagerank": 0.00905721082396169, "clustering_coefficient": 0}, "id": "Christopher LG Hill"}, {"gender": "f", "nationality": "Czech Republic", "year": 2003.0, "centrality_measures": {"degree_centrality": 0.057777777777777775, "closeness_centrality": 0.05807407407407408, "betweenness_centrality": 0.00014550264550264547, "eigenvector_centrality": 0.27991980238631176, "pagerank": 0.010536118773807331, "clustering_coefficient": 0.8717948717948718}, "id": "Pavla Scerankov\u00e1"}, {"gender": "m", "nationality": "Czech Republic", "year": 2003.0, "centrality_measures": {"degree_centrality": 0.05333333333333333, "closeness_centrality": 0.05444444444444444, "betweenness_centrality": 0.0, "eigenvector_centrality": 0.27460817448713837, "pagerank": 0.009576056929916374, "clustering_coefficient": 1.0}, "id": "Vasil Artamonov"}, {"gender": "m", "nationality": "Czech Republic", "year": 2003.0, "centrality_measures": {"degree_centrality": 0.05333333333333333, "closeness_centrality": 0.05444444444444444, "betweenness_centrality": 0.0, "eigenvector_centrality": 0.27460817448713837, "pagerank": 0.009576056929916374, "clustering_coefficient": 1.0}, "id": "Dominik Lang"}, {"gender": "m", "nationality": NaN, "year": 2003.0, "centrality_measures": {"degree_centrality": 0.0, "closeness_centrality": 0.0, "betweenness_centrality": 0.0, "eigenvector_centrality": 5.5724414651128046e-27, "pagerank": 0.0013591987194371152, "clustering_coefficient": 0}, "id": "David Wallace"}, {"gender": "f", "nationality": "Italy", "year": 2003.0, "centrality_measures": {"degree_centrality": 0.0044444444444444444, "closeness_centrality": 0.0044444444444444444, "betweenness_centrality": 0.0, "eigenvector_centrality": 4.6745027053776994e-20, "pagerank": 0.00905721082396169, "clustering_coefficient": 0}, "id": "Elisa Rossi"}, {"gender": "m", "nationality": "USA", "year": 2003.0, "centrality_measures": {"degree_centrality": 0.0, "closeness_centrality": 0.0, "betweenness_centrality": 0.0, "eigenvector_centrality": 5.5724414651128046e-27, "pagerank": 0.0013591987194371152, "clustering_coefficient": 0}, "id": "David Wilson"}, {"gender": "f", "nationality": "USA", "year": 2003.0, "centrality_measures": {"degree_centrality": 0.0, "closeness_centrality": 0.0, "betweenness_centrality": 0.0, "eigenvector_centrality": 5.5724414651128046e-27, "pagerank": 0.0013591987194371152, "clustering_coefficient": 0}, "id": "Margie Livingston"}, {"gender": "m", "nationality": "United Kingdom", "year": 2003.0, "centrality_measures": {"degree_centrality": 0.0, "closeness_centrality": 0.0, "betweenness_centrality": 0.0, "eigenvector_centrality": 5.5724414651128046e-27, "pagerank": 0.0013591987194371152, "clustering_coefficient": 0}, "id": "Damien Roach"}, {"gender": "f", "nationality": "Canada", "year": 2003.0, "centrality_measures": {"degree_centrality": 0.0, "closeness_centrality": 0.0, "betweenness_centrality": 0.0, "eigenvector_centrality": 5.5724414651128046e-27, "pagerank": 0.0013591987194371152, "clustering_coefficient": 0}, "id": "M\u00e9lanie Rocan"}, {"gender": "m", "nationality": "Germany", "year": 2003.0, "centrality_measures": {"degree_centrality": 0.017777777777777778, "closeness_centrality": 0.017777777777777778, "betweenness_centrality": 0.0, "eigenvector_centrality": 1.8180875376242893e-10, "pagerank": 0.008687999339811495, "clustering_coefficient": 1.0}, "id": "Nadim Vardag"}, {"gender": "m", "nationality": "Brazil", "year": 2003.0, "centrality_measures": {"degree_centrality": 0.0, "closeness_centrality": 0.0, "betweenness_centrality": 0.0, "eigenvector_centrality": 5.5724414651128046e-27, "pagerank": 0.0013591987194371152, "clustering_coefficient": 0}, "id": "Marcone Moreira"}, {"gender": "m", "nationality": "Brazil", "year": 2003.0, "centrality_measures": {"degree_centrality": 0.0, "closeness_centrality": 0.0, "betweenness_centrality": 0.0, "eigenvector_centrality": 5.5724414651128046e-27, "pagerank": 0.0013591987194371152, "clustering_coefficient": 0}, "id": "Marcellvs L."}, {"gender": "m", "nationality": "United Kingdom", "year": 2003.0, "centrality_measures": {"degree_centrality": 0.0, "closeness_centrality": 0.0, "betweenness_centrality": 0.0, "eigenvector_centrality": 5.5724414651128046e-27, "pagerank": 0.0013591987194371152, "clustering_coefficient": 0}, "id": "Joe Clark"}, {"gender": "m", "nationality": "Bosnia and Herzegovina", "year": 2003.0, "centrality_measures": {"degree_centrality": 0.0, "closeness_centrality": 0.0, "betweenness_centrality": 0.0, "eigenvector_centrality": 5.5724414651128046e-27, "pagerank": 0.0013591987194371152, "clustering_coefficient": 0}, "id": "Gordan Savicic"}, {"gender": "f", "nationality": "Denmark", "year": 2003.0, "centrality_measures": {"degree_centrality": 0.017777777777777778, "closeness_centrality": 0.017777777777777778, "betweenness_centrality": 0.0, "eigenvector_centrality": 1.8180875376242893e-10, "pagerank": 0.008687999339811495, "clustering_coefficient": 1.0}, "id": "Tove Storch"}, {"gender": "m", "nationality": "USA", "year": 2003.0, "centrality_measures": {"degree_centrality": 0.0, "closeness_centrality": 0.0, "betweenness_centrality": 0.0, "eigenvector_centrality": 5.5724414651128046e-27, "pagerank": 0.0013591987194371152, "clustering_coefficient": 0}, "id": "Charley Friedman"}, {"gender": "f", "nationality": "Germany", "year": 2003.0, "centrality_measures": {"degree_centrality": 0.0, "closeness_centrality": 0.0, "betweenness_centrality": 0.0, "eigenvector_centrality": 5.5724414651128046e-27, "pagerank": 0.0013591987194371152, "clustering_coefficient": 0}, "id": "Kathrin Sonntag"}, {"gender": "m", "nationality": "Israel", "year": 2003.0, "centrality_measures": {"degree_centrality": 0.0, "closeness_centrality": 0.0, "betweenness_centrality": 0.0, "eigenvector_centrality": 5.5724414651128046e-27, "pagerank": 0.0013591987194371152, "clustering_coefficient": 0}, "id": "Ariel Schlesinger"}, {"gender": "m", "nationality": "Spain", "year": 2003.0, "centrality_measures": {"degree_centrality": 0.0, "closeness_centrality": 0.0, "betweenness_centrality": 0.0, "eigenvector_centrality": 5.5724414651128046e-27, "pagerank": 0.0013591987194371152, "clustering_coefficient": 0}, "id": "Daniel Silvo"}, {"gender": "f", "nationality": "China", "year": 2003.0, "centrality_measures": {"degree_centrality": 0.0044444444444444444, "closeness_centrality": 0.0044444444444444444, "betweenness_centrality": 0.0, "eigenvector_centrality": 4.6745027053776994e-20, "pagerank": 0.00905721082396169, "clustering_coefficient": 0}, "id": "Li Shurui"}, {"gender": "m", "nationality": "Germany", "year": 2003.0, "centrality_measures": {"degree_centrality": 0.0, "closeness_centrality": 0.0, "betweenness_centrality": 0.0, "eigenvector_centrality": 5.5724414651128046e-27, "pagerank": 0.0013591987194371152, "clustering_coefficient": 0}, "id": "Johann B\u7aefsen"}, {"gender": "m", "nationality": NaN, "year": 2003.0, "centrality_measures": {"degree_centrality": 0.0, "closeness_centrality": 0.0, "betweenness_centrality": 0.0, "eigenvector_centrality": 5.5724414651128046e-27, "pagerank": 0.0013591987194371152, "clustering_coefficient": 0}, "id": "Wang Chen"}, {"gender": "m", "nationality": "Belgium", "year": 2003.0, "centrality_measures": {"degree_centrality": 0.0044444444444444444, "closeness_centrality": 0.0044444444444444444, "betweenness_centrality": 0.0, "eigenvector_centrality": 4.6745027053776994e-20, "pagerank": 0.00905721082396169, "clustering_coefficient": 0}, "id": "Matthieu Ronsse"}, {"gender": "m", "nationality": "China", "year": 2003.0, "centrality_measures": {"degree_centrality": 0.0, "closeness_centrality": 0.0, "betweenness_centrality": 0.0, "eigenvector_centrality": 5.5724414651128046e-27, "pagerank": 0.0013591987194371152, "clustering_coefficient": 0}, "id": "Wei Chen"}, {"gender": "f", "nationality": "Italy", "year": 2003.0, "centrality_measures": {"degree_centrality": 0.0, "closeness_centrality": 0.0, "betweenness_centrality": 0.0, "eigenvector_centrality": 5.5724414651128046e-27, "pagerank": 0.0013591987194371152, "clustering_coefficient": 0}, "id": "Simone Catania"}, {"gender": "m", "nationality": "USA", "year": 2003.0, "centrality_measures": {"degree_centrality": 0.0, "closeness_centrality": 0.0, "betweenness_centrality": 0.0, "eigenvector_centrality": 5.5724414651128046e-27, "pagerank": 0.0013591987194371152, "clustering_coefficient": 0}, "id": "Daniel Gordon"}, {"gender": "f", "nationality": "Australia", "year": 2003.0, "centrality_measures": {"degree_centrality": 0.0044444444444444444, "closeness_centrality": 0.0044444444444444444, "betweenness_centrality": 0.0, "eigenvector_centrality": 4.6745027053776994e-20, "pagerank": 0.00905721082396169, "clustering_coefficient": 0}, "id": "Kate Rohde"}, {"gender": "m", "nationality": "Belgium", "year": 2003.0, "centrality_measures": {"degree_centrality": 0.0044444444444444444, "closeness_centrality": 0.0044444444444444444, "betweenness_centrality": 0.0, "eigenvector_centrality": 4.6745027053776994e-20, "pagerank": 0.00905721082396169, "clustering_coefficient": 0}, "id": "Nick Ervinck"}, {"gender": "f", "nationality": "Latvia", "year": 2003.0, "centrality_measures": {"degree_centrality": 0.0, "closeness_centrality": 0.0, "betweenness_centrality": 0.0, "eigenvector_centrality": 5.5724414651128046e-27, "pagerank": 0.0013591987194371152, "clustering_coefficient": 0}, "id": "Kristine Alksne"}, {"gender": "m", "nationality": "Slovenia", "year": 2003.0, "centrality_measures": {"degree_centrality": 0.0, "closeness_centrality": 0.0, "betweenness_centrality": 0.0, "eigenvector_centrality": 5.5724414651128046e-27, "pagerank": 0.0013591987194371152, "clustering_coefficient": 0}, "id": "Istvan Ist Huzjan"}, {"gender": "m", "nationality": "Russia", "year": 2003.0, "centrality_measures": {"degree_centrality": 0.04, "closeness_centrality": 0.04, "betweenness_centrality": 0.00031746031746031746, "eigenvector_centrality": 5.2461858379707427e-05, "pagerank": 0.011576119897363164, "clustering_coefficient": 0.7777777777777778}, "id": "Vladimir Logutov"}, {"gender": "f", "nationality": "Denmark", "year": 2003.0, "centrality_measures": {"degree_centrality": 0.0044444444444444444, "closeness_centrality": 0.0044444444444444444, "betweenness_centrality": 0.0, "eigenvector_centrality": 4.6745027053776994e-20, "pagerank": 0.00905721082396169, "clustering_coefficient": 0}, "id": "Ditte Ejlerskov"}, {"gender": "f", "nationality": "Austria", "year": 2003.0, "centrality_measures": {"degree_centrality": 0.0, "closeness_centrality": 0.0, "betweenness_centrality": 0.0, "eigenvector_centrality": 5.5724414651128046e-27, "pagerank": 0.0013591987194371152, "clustering_coefficient": 0}, "id": "Johanna Kirsch"}, {"gender": "m", "nationality": "USA", "year": 2003.0, "centrality_measures": {"degree_centrality": 0.017777777777777778, "closeness_centrality": 0.01851851851851852, "betweenness_centrality": 0.0, "eigenvector_centrality": 8.628033669392661e-11, "pagerank": 0.009597373066347566, "clustering_coefficient": 1.0}, "id": "Mathew Cerletty"}, {"gender": "f", "nationality": "Finland", "year": 2003.0, "centrality_measures": {"degree_centrality": 0.0, "closeness_centrality": 0.0, "betweenness_centrality": 0.0, "eigenvector_centrality": 5.5724414651128046e-27, "pagerank": 0.0013591987194371152, "clustering_coefficient": 0}, "id": "Anni Lepp\ucc44l\ucc44"}, {"gender": "m", "nationality": "Austria", "year": 2003.0, "centrality_measures": {"degree_centrality": 0.0, "closeness_centrality": 0.0, "betweenness_centrality": 0.0, "eigenvector_centrality": 5.5724414651128046e-27, "pagerank": 0.0013591987194371152, "clustering_coefficient": 0}, "id": "Bernd Oppl"}, {"gender": "m", "nationality": NaN, "year": 2003.0, "centrality_measures": {"degree_centrality": 0.035555555555555556, "closeness_centrality": 0.036000000000000004, "betweenness_centrality": 0.0, "eigenvector_centrality": 5.173563042593662e-05, "pagerank": 0.00956794035321134, "clustering_coefficient": 1.0}, "id": "Gordon Castellane"}, {"gender": "f", "nationality": "Germany", "year": 2003.0, "centrality_measures": {"degree_centrality": 0.035555555555555556, "closeness_centrality": 0.036000000000000004, "betweenness_centrality": 0.0, "eigenvector_centrality": 5.173563042593662e-05, "pagerank": 0.00956794035321134, "clustering_coefficient": 1.0}, "id": "Swantje Hielscher"}, {"gender": "m", "nationality": "Switzerland", "year": 2003.0, "centrality_measures": {"degree_centrality": 0.035555555555555556, "closeness_centrality": 0.036000000000000004, "betweenness_centrality": 0.0, "eigenvector_centrality": 5.173563042593662e-05, "pagerank": 0.00956794035321134, "clustering_coefficient": 1.0}, "id": "Guillaume Pilet"}, {"gender": "m", "nationality": "United Kingdom", "year": 2003.0, "centrality_measures": {"degree_centrality": 0.0044444444444444444, "closeness_centrality": 0.0044444444444444444, "betweenness_centrality": 0.0, "eigenvector_centrality": 4.6745027053776994e-20, "pagerank": 0.00905721082396169, "clustering_coefficient": 0}, "id": "James Ryan"}, {"gender": "m", "nationality": "Mexico", "year": 2003.0, "centrality_measures": {"degree_centrality": 0.0, "closeness_centrality": 0.0, "betweenness_centrality": 0.0, "eigenvector_centrality": 5.5724414651128046e-27, "pagerank": 0.0013591987194371152, "clustering_coefficient": 0}, "id": "Joaquin Segura"}, {"gender": "f", "nationality": "USA", "year": 2003.0, "centrality_measures": {"degree_centrality": 0.0, "closeness_centrality": 0.0, "betweenness_centrality": 0.0, "eigenvector_centrality": 5.5724414651128046e-27, "pagerank": 0.0013591987194371152, "clustering_coefficient": 0}, "id": "Jennifer Lacey"}, {"gender": "f", "nationality": "Germany", "year": 2003.0, "centrality_measures": {"degree_centrality": 0.0, "closeness_centrality": 0.0, "betweenness_centrality": 0.0, "eigenvector_centrality": 5.5724414651128046e-27, "pagerank": 0.0013591987194371152, "clustering_coefficient": 0}, "id": "Mia Unverzagt"}, {"gender": "f", "nationality": "Austria", "year": 2003.0, "centrality_measures": {"degree_centrality": 0.017777777777777778, "closeness_centrality": 0.017777777777777778, "betweenness_centrality": 0.0, "eigenvector_centrality": 1.8180875376242893e-10, "pagerank": 0.008687999339811495, "clustering_coefficient": 1.0}, "id": "Katharina Heistinger"}, {"gender": "f", "nationality": "France", "year": 2003.0, "centrality_measures": {"degree_centrality": 0.0, "closeness_centrality": 0.0, "betweenness_centrality": 0.0, "eigenvector_centrality": 5.5724414651128046e-27, "pagerank": 0.0013591987194371152, "clustering_coefficient": 0}, "id": "Marianne Maric"}, {"gender": "m", "nationality": "Germany", "year": 2003.0, "centrality_measures": {"degree_centrality": 0.0044444444444444444, "closeness_centrality": 0.0044444444444444444, "betweenness_centrality": 0.0, "eigenvector_centrality": 4.6745027053776994e-20, "pagerank": 0.00905721082396169, "clustering_coefficient": 0}, "id": "Simon Mullan"}, {"gender": "f", "nationality": "India", "year": 2003.0, "centrality_measures": {"degree_centrality": 0.0, "closeness_centrality": 0.0, "betweenness_centrality": 0.0, "eigenvector_centrality": 5.5724414651128046e-27, "pagerank": 0.0013591987194371152, "clustering_coefficient": 0}, "id": "Sumakshi Singh"}, {"gender": "f", "nationality": "Austria", "year": 2003.0, "centrality_measures": {"degree_centrality": 0.0, "closeness_centrality": 0.0, "betweenness_centrality": 0.0, "eigenvector_centrality": 5.5724414651128046e-27, "pagerank": 0.0013591987194371152, "clustering_coefficient": 0}, "id": "Linda Thalmann"}, {"gender": "m", "nationality": "USA", "year": 2003.0, "centrality_measures": {"degree_centrality": 0.0, "closeness_centrality": 0.0, "betweenness_centrality": 0.0, "eigenvector_centrality": 5.5724414651128046e-27, "pagerank": 0.0013591987194371152, "clustering_coefficient": 0}, "id": "Johannes VanDerBeek"}, {"gender": "f", "nationality": "France", "year": 2003.0, "centrality_measures": {"degree_centrality": 0.017777777777777778, "closeness_centrality": 0.017777777777777778, "betweenness_centrality": 0.0, "eigenvector_centrality": 6.64286788119412e-11, "pagerank": 0.00905721082396169, "clustering_coefficient": 1.0}, "id": "Roxane Borujerdi"}, {"gender": "m", "nationality": "USA", "year": 2003.0, "centrality_measures": {"degree_centrality": 0.022222222222222223, "closeness_centrality": 0.022222222222222223, "betweenness_centrality": 0.00015873015873015873, "eigenvector_centrality": 9.071292356789267e-11, "pagerank": 0.01247412689846257, "clustering_coefficient": 0.6}, "id": "Matt Leines"}, {"gender": "f", "nationality": "Romania", "year": 2003.0, "centrality_measures": {"degree_centrality": 0.0, "closeness_centrality": 0.0, "betweenness_centrality": 0.0, "eigenvector_centrality": 5.5724414651128046e-27, "pagerank": 0.0013591987194371152, "clustering_coefficient": 0}, "id": "Oana Farcas"}, {"gender": "m", "nationality": "Canada", "year": 2003.0, "centrality_measures": {"degree_centrality": 0.017777777777777778, "closeness_centrality": 0.017777777777777778, "betweenness_centrality": 0.0, "eigenvector_centrality": 6.64286788119412e-11, "pagerank": 0.00905721082396169, "clustering_coefficient": 1.0}, "id": "Daniel Domig"}, {"gender": "f", "nationality": "Austria", "year": 2003.0, "centrality_measures": {"degree_centrality": 0.008888888888888889, "closeness_centrality": 0.008888888888888889, "betweenness_centrality": 0.0, "eigenvector_centrality": 5.246073533531044e-16, "pagerank": 0.00905721082396169, "clustering_coefficient": 1.0}, "id": "Manuela Gernedel"}, {"gender": "f", "nationality": "Germany", "year": 2003.0, "centrality_measures": {"degree_centrality": 0.008888888888888889, "closeness_centrality": 0.008888888888888889, "betweenness_centrality": 0.0, "eigenvector_centrality": 5.246073533531044e-16, "pagerank": 0.00905721082396169, "clustering_coefficient": 1.0}, "id": "Anna Witt"}, {"gender": "m", "nationality": "Switzerland", "year": 2003.0, "centrality_measures": {"degree_centrality": 0.035555555555555556, "closeness_centrality": 0.036000000000000004, "betweenness_centrality": 0.0, "eigenvector_centrality": 5.173563042593662e-05, "pagerank": 0.00956794035321134, "clustering_coefficient": 1.0}, "id": "Tatiana Arce"}, {"gender": "m", "nationality": "Belgium", "year": 2003.0, "centrality_measures": {"degree_centrality": 0.0, "closeness_centrality": 0.0, "betweenness_centrality": 0.0, "eigenvector_centrality": 5.5724414651128046e-27, "pagerank": 0.0013591987194371152, "clustering_coefficient": 0}, "id": "Abdul Vas"}, {"gender": "m", "nationality": "Belgium", "year": 2003.0, "centrality_measures": {"degree_centrality": 0.0, "closeness_centrality": 0.0, "betweenness_centrality": 0.0, "eigenvector_centrality": 5.5724414651128046e-27, "pagerank": 0.0013591987194371152, "clustering_coefficient": 0}, "id": "Pieterjan Ginckels"}, {"gender": "f", "nationality": "Serbia", "year": 2003.0, "centrality_measures": {"degree_centrality": 0.0, "closeness_centrality": 0.0, "betweenness_centrality": 0.0, "eigenvector_centrality": 5.5724414651128046e-27, "pagerank": 0.0013591987194371152, "clustering_coefficient": 0}, "id": "Ivana Smiljanic"}, {"gender": "f", "nationality": "Canada", "year": 2003.0, "centrality_measures": {"degree_centrality": 0.0, "closeness_centrality": 0.0, "betweenness_centrality": 0.0, "eigenvector_centrality": 5.5724414651128046e-27, "pagerank": 0.0013591987194371152, "clustering_coefficient": 0}, "id": "Amy Wong"}, {"gender": "f", "nationality": "Czech Republic", "year": 2003.0, "centrality_measures": {"degree_centrality": 0.0, "closeness_centrality": 0.0, "betweenness_centrality": 0.0, "eigenvector_centrality": 5.5724414651128046e-27, "pagerank": 0.0013591987194371152, "clustering_coefficient": 0}, "id": "Laura Samaraweerov\u00e1"}, {"gender": "m", "nationality": NaN, "year": 2003.0, "centrality_measures": {"degree_centrality": 0.0044444444444444444, "closeness_centrality": 0.0044444444444444444, "betweenness_centrality": 0.0, "eigenvector_centrality": 4.6745027053776994e-20, "pagerank": 0.00905721082396169, "clustering_coefficient": 0}, "id": "Michael Niemetz"}, {"gender": "m", "nationality": "Germany", "year": 2003.0, "centrality_measures": {"degree_centrality": 0.0, "closeness_centrality": 0.0, "betweenness_centrality": 0.0, "eigenvector_centrality": 5.5724414651128046e-27, "pagerank": 0.0013591987194371152, "clustering_coefficient": 0}, "id": "Ono Ludwig"}, {"gender": "m", "nationality": "Czech Republic", "year": 2003.0, "centrality_measures": {"degree_centrality": 0.057777777777777775, "closeness_centrality": 0.05807407407407408, "betweenness_centrality": 0.0002380952380952381, "eigenvector_centrality": 0.27812657478497466, "pagerank": 0.010726883411221803, "clustering_coefficient": 0.8589743589743589}, "id": "Evzen Simera"}, {"gender": "m", "nationality": "Czech Republic", "year": 2003.0, "centrality_measures": {"degree_centrality": 0.05333333333333333, "closeness_centrality": 0.05444444444444444, "betweenness_centrality": 0.0, "eigenvector_centrality": 0.27460817448713837, "pagerank": 0.009576056929916374, "clustering_coefficient": 1.0}, "id": "Adam Stech"}, {"gender": "f", "nationality": "Czech Republic", "year": 2003.0, "centrality_measures": {"degree_centrality": 0.013333333333333332, "closeness_centrality": 0.0335042735042735, "betweenness_centrality": 0.0, "eigenvector_centrality": 0.06949549410586443, "pagerank": 0.003425731436303995, "clustering_coefficient": 1.0}, "id": "Pavla Gajdosikova"}, {"gender": "m", "nationality": "Australia", "year": 2003.0, "centrality_measures": {"degree_centrality": 0.0, "closeness_centrality": 0.0, "betweenness_centrality": 0.0, "eigenvector_centrality": 5.5724414651128046e-27, "pagerank": 0.0013591987194371152, "clustering_coefficient": 0}, "id": "Sebastian Koch"}, {"gender": "f", "nationality": "France", "year": 2003.0, "centrality_measures": {"degree_centrality": 0.0, "closeness_centrality": 0.0, "betweenness_centrality": 0.0, "eigenvector_centrality": 5.5724414651128046e-27, "pagerank": 0.0013591987194371152, "clustering_coefficient": 0}, "id": "Emma Dusong"}, {"gender": "m", "nationality": "Slovakia", "year": 2003.0, "centrality_measures": {"degree_centrality": 0.013333333333333332, "closeness_centrality": 0.013333333333333334, "betweenness_centrality": 0.0, "eigenvector_centrality": 3.921257079035301e-13, "pagerank": 0.00905721082396169, "clustering_coefficient": 1.0}, "id": "Ivan Dudas"}, {"gender": "f", "nationality": "Denmark", "year": 2003.0, "centrality_measures": {"degree_centrality": 0.0, "closeness_centrality": 0.0, "betweenness_centrality": 0.0, "eigenvector_centrality": 5.5724414651128046e-27, "pagerank": 0.0013591987194371152, "clustering_coefficient": 0}, "id": "Sidsel Meineche Hansen"}, {"gender": "m", "nationality": "Germany", "year": 2003.0, "centrality_measures": {"degree_centrality": 0.0, "closeness_centrality": 0.0, "betweenness_centrality": 0.0, "eigenvector_centrality": 5.5724414651128046e-27, "pagerank": 0.0013591987194371152, "clustering_coefficient": 0}, "id": "Alexander Voigt"}, {"gender": "f", "nationality": "Italy", "year": 2003.0, "centrality_measures": {"degree_centrality": 0.0, "closeness_centrality": 0.0, "betweenness_centrality": 0.0, "eigenvector_centrality": 5.5724414651128046e-27, "pagerank": 0.0013591987194371152, "clustering_coefficient": 0}, "id": "Valentina Sonzogni"}, {"gender": "m", "nationality": NaN, "year": 2003.0, "centrality_measures": {"degree_centrality": 0.008888888888888889, "closeness_centrality": 0.032263374485596706, "betweenness_centrality": 0.0, "eigenvector_centrality": 0.04603352715998881, "pagerank": 0.0027618523399247827, "clustering_coefficient": 1.0}, "id": "Vladim\u00edr V\u00e9la"}, {"gender": "m", "nationality": "Slovakia", "year": 2003.0, "centrality_measures": {"degree_centrality": 0.013333333333333332, "closeness_centrality": 0.013333333333333334, "betweenness_centrality": 0.0, "eigenvector_centrality": 3.921257079035301e-13, "pagerank": 0.00905721082396169, "clustering_coefficient": 1.0}, "id": "Matej Longauer"}, {"gender": "m", "nationality": "Slovakia", "year": 2003.0, "centrality_measures": {"degree_centrality": 0.013333333333333332, "closeness_centrality": 0.013333333333333334, "betweenness_centrality": 0.0, "eigenvector_centrality": 3.921257079035301e-13, "pagerank": 0.00905721082396169, "clustering_coefficient": 1.0}, "id": "Tom\u00e1s Makara"}, {"gender": "m", "nationality": "USA", "year": 2003.0, "centrality_measures": {"degree_centrality": 0.0, "closeness_centrality": 0.0, "betweenness_centrality": 0.0, "eigenvector_centrality": 5.5724414651128046e-27, "pagerank": 0.0013591987194371152, "clustering_coefficient": 0}, "id": "Bill Jenkins"}, {"gender": "f", "nationality": "USA", "year": 2003.0, "centrality_measures": {"degree_centrality": 0.0, "closeness_centrality": 0.0, "betweenness_centrality": 0.0, "eigenvector_centrality": 5.5724414651128046e-27, "pagerank": 0.0013591987194371152, "clustering_coefficient": 0}, "id": "Christine Wang"}, {"gender": "m", "nationality": NaN, "year": 2003.0, "centrality_measures": {"degree_centrality": 0.008888888888888889, "closeness_centrality": 0.008888888888888889, "betweenness_centrality": 0.0, "eigenvector_centrality": 5.246073533531044e-16, "pagerank": 0.00905721082396169, "clustering_coefficient": 1.0}, "id": "Lukas Schneider"}, {"gender": "f", "nationality": "Taiwan", "year": 2003.0, "centrality_measures": {"degree_centrality": 0.0, "closeness_centrality": 0.0, "betweenness_centrality": 0.0, "eigenvector_centrality": 5.5724414651128046e-27, "pagerank": 0.0013591987194371152, "clustering_coefficient": 0}, "id": "Peishan Wu"}, {"gender": "f", "nationality": "Slovakia", "year": 2003.0, "centrality_measures": {"degree_centrality": 0.008888888888888889, "closeness_centrality": 0.008888888888888889, "betweenness_centrality": 0.0, "eigenvector_centrality": 5.246073533531044e-16, "pagerank": 0.00905721082396169, "clustering_coefficient": 1.0}, "id": "Andrea Junekov\u00e1"}, {"gender": "m", "nationality": "Slovakia", "year": 2003.0, "centrality_measures": {"degree_centrality": 0.008888888888888889, "closeness_centrality": 0.008888888888888889, "betweenness_centrality": 0.0, "eigenvector_centrality": 5.246073533531044e-16, "pagerank": 0.00905721082396169, "clustering_coefficient": 1.0}, "id": "Juraj Anusev"}, {"gender": "m", "nationality": "Denmark", "year": 2003.0, "centrality_measures": {"degree_centrality": 0.0, "closeness_centrality": 0.0, "betweenness_centrality": 0.0, "eigenvector_centrality": 5.5724414651128046e-27, "pagerank": 0.0013591987194371152, "clustering_coefficient": 0}, "id": "Rasmus Knud"}, {"gender": "m", "nationality": "United Kingdom", "year": 2003.0, "centrality_measures": {"degree_centrality": 0.0, "closeness_centrality": 0.0, "betweenness_centrality": 0.0, "eigenvector_centrality": 5.5724414651128046e-27, "pagerank": 0.0013591987194371152, "clustering_coefficient": 0}, "id": "David Jones"}, {"gender": "f", "nationality": "USA", "year": 2003.0, "centrality_measures": {"degree_centrality": 0.0, "closeness_centrality": 0.0, "betweenness_centrality": 0.0, "eigenvector_centrality": 5.5724414651128046e-27, "pagerank": 0.0013591987194371152, "clustering_coefficient": 0}, "id": "Alex McQuilkin"}, {"gender": "m", "nationality": "China", "year": 2003.0, "centrality_measures": {"degree_centrality": 0.0044444444444444444, "closeness_centrality": 0.0044444444444444444, "betweenness_centrality": 0.0, "eigenvector_centrality": 4.6745027053776994e-20, "pagerank": 0.00905721082396169, "clustering_coefficient": 0}, "id": "Yan Lei"}, {"gender": "m", "nationality": "Germany", "year": 2003.0, "centrality_measures": {"degree_centrality": 0.0, "closeness_centrality": 0.0, "betweenness_centrality": 0.0, "eigenvector_centrality": 5.5724414651128046e-27, "pagerank": 0.0013591987194371152, "clustering_coefficient": 0}, "id": "Thilo Westermann"}, {"gender": "f", "nationality": "Czech Republic", "year": 2003.0, "centrality_measures": {"degree_centrality": 0.05333333333333333, "closeness_centrality": 0.05444444444444444, "betweenness_centrality": 0.0, "eigenvector_centrality": 0.27460817448713837, "pagerank": 0.009576056929916374, "clustering_coefficient": 1.0}, "id": "Eva Kotatkova"}, {"gender": "m", "nationality": "New Zealand", "year": 2003.0, "centrality_measures": {"degree_centrality": 0.0, "closeness_centrality": 0.0, "betweenness_centrality": 0.0, "eigenvector_centrality": 5.5724414651128046e-27, "pagerank": 0.0013591987194371152, "clustering_coefficient": 0}, "id": "Andrew Thomas"}, {"gender": "m", "nationality": "Australia", "year": 2003.0, "centrality_measures": {"degree_centrality": 0.0, "closeness_centrality": 0.0, "betweenness_centrality": 0.0, "eigenvector_centrality": 5.5724414651128046e-27, "pagerank": 0.0013591987194371152, "clustering_coefficient": 0}, "id": "Fergus Binns"}, {"gender": "m", "nationality": "Germany", "year": 2003.0, "centrality_measures": {"degree_centrality": 0.0, "closeness_centrality": 0.0, "betweenness_centrality": 0.0, "eigenvector_centrality": 5.5724414651128046e-27, "pagerank": 0.0013591987194371152, "clustering_coefficient": 0}, "id": "Philipp Kremer"}, {"gender": "f", "nationality": "Russia", "year": 2003.0, "centrality_measures": {"degree_centrality": 0.0, "closeness_centrality": 0.0, "betweenness_centrality": 0.0, "eigenvector_centrality": 5.5724414651128046e-27, "pagerank": 0.0013591987194371152, "clustering_coefficient": 0}, "id": "Aleksandra Fedorova"}, {"gender": "m", "nationality": "Canada", "year": 2003.0, "centrality_measures": {"degree_centrality": 0.0, "closeness_centrality": 0.0, "betweenness_centrality": 0.0, "eigenvector_centrality": 5.5724414651128046e-27, "pagerank": 0.0013591987194371152, "clustering_coefficient": 0}, "id": "James Paterson"}, {"gender": "f", "nationality": "Ukraine", "year": 2003.0, "centrality_measures": {"degree_centrality": 0.0, "closeness_centrality": 0.0, "betweenness_centrality": 0.0, "eigenvector_centrality": 5.5724414651128046e-27, "pagerank": 0.0013591987194371152, "clustering_coefficient": 0}, "id": "Maryna Baranovska"}, {"gender": "f", "nationality": "Australia", "year": 2003.0, "centrality_measures": {"degree_centrality": 0.0, "closeness_centrality": 0.0, "betweenness_centrality": 0.0, "eigenvector_centrality": 5.5724414651128046e-27, "pagerank": 0.0013591987194371152, "clustering_coefficient": 0}, "id": "Samantha Hobson"}, {"gender": "m", "nationality": "Slovakia", "year": 2003.0, "centrality_measures": {"degree_centrality": 0.0, "closeness_centrality": 0.0, "betweenness_centrality": 0.0, "eigenvector_centrality": 5.5724414651128046e-27, "pagerank": 0.0013591987194371152, "clustering_coefficient": 0}, "id": "Rastislav Sedlacik"}, {"gender": "f", "nationality": "USA", "year": 2003.0, "centrality_measures": {"degree_centrality": 0.0, "closeness_centrality": 0.0, "betweenness_centrality": 0.0, "eigenvector_centrality": 5.5724414651128046e-27, "pagerank": 0.0013591987194371152, "clustering_coefficient": 0}, "id": "Hannah Dougherty"}, {"gender": "f", "nationality": "Germany", "year": 2003.0, "centrality_measures": {"degree_centrality": 0.008888888888888889, "closeness_centrality": 0.008888888888888889, "betweenness_centrality": 0.0, "eigenvector_centrality": 5.246073533531044e-16, "pagerank": 0.00905721082396169, "clustering_coefficient": 1.0}, "id": "Lisa Erb"}, {"gender": "m", "nationality": "Russia", "year": 2003.0, "centrality_measures": {"degree_centrality": 0.0, "closeness_centrality": 0.0, "betweenness_centrality": 0.0, "eigenvector_centrality": 5.5724414651128046e-27, "pagerank": 0.0013591987194371152, "clustering_coefficient": 0}, "id": "Denis Salautin"}, {"gender": "f", "nationality": "Germany", "year": 2003.0, "centrality_measures": {"degree_centrality": 0.0, "closeness_centrality": 0.0, "betweenness_centrality": 0.0, "eigenvector_centrality": 5.5724414651128046e-27, "pagerank": 0.0013591987194371152, "clustering_coefficient": 0}, "id": "Ramona Schintzel"}, {"gender": "m", "nationality": "Russia", "year": 2003.0, "centrality_measures": {"degree_centrality": 0.0044444444444444444, "closeness_centrality": 0.021176470588235293, "betweenness_centrality": 0.0, "eigenvector_centrality": 6.546245855013063e-06, "pagerank": 0.0024524655165630055, "clustering_coefficient": 0}, "id": "Andrey Syailev"}, {"gender": "f", "nationality": "Austria", "year": 2003.0, "centrality_measures": {"degree_centrality": 0.008888888888888889, "closeness_centrality": 0.008888888888888889, "betweenness_centrality": 0.0, "eigenvector_centrality": 5.246073533531044e-16, "pagerank": 0.00905721082396169, "clustering_coefficient": 1.0}, "id": "Iris Nemecek"}, {"gender": "m", "nationality": "Mexico", "year": 2003.0, "centrality_measures": {"degree_centrality": 0.0044444444444444444, "closeness_centrality": 0.0044444444444444444, "betweenness_centrality": 0.0, "eigenvector_centrality": 4.6745027053776994e-20, "pagerank": 0.00905721082396169, "clustering_coefficient": 0}, "id": "I\u00f1aki Bonillas"}, {"gender": "m", "nationality": "USA", "year": 2003.0, "centrality_measures": {"degree_centrality": 0.0, "closeness_centrality": 0.0, "betweenness_centrality": 0.0, "eigenvector_centrality": 5.5724414651128046e-27, "pagerank": 0.0013591987194371152, "clustering_coefficient": 0}, "id": "Adam Green"}, {"gender": "m", "nationality": "China", "year": 2003.0, "centrality_measures": {"degree_centrality": 0.0044444444444444444, "closeness_centrality": 0.0044444444444444444, "betweenness_centrality": 0.0, "eigenvector_centrality": 4.6745027053776994e-20, "pagerank": 0.00905721082396169, "clustering_coefficient": 0}, "id": "Liang Hao"}, {"gender": "m", "nationality": "Austria", "year": 2003.0, "centrality_measures": {"degree_centrality": 0.008888888888888889, "closeness_centrality": 0.008888888888888889, "betweenness_centrality": 0.0, "eigenvector_centrality": 5.246073533531044e-16, "pagerank": 0.00905721082396169, "clustering_coefficient": 1.0}, "id": "Alfredo Barsuglia"}, {"gender": "m", "nationality": "Austria", "year": 2003.0, "centrality_measures": {"degree_centrality": 0.008888888888888889, "closeness_centrality": 0.008888888888888889, "betweenness_centrality": 0.0, "eigenvector_centrality": 5.246073533531044e-16, "pagerank": 0.00905721082396169, "clustering_coefficient": 1.0}, "id": "Robert Muntean"}, {"gender": "m", "nationality": "Czech Republic", "year": 2003.0, "centrality_measures": {"degree_centrality": 0.057777777777777775, "closeness_centrality": 0.05807407407407408, "betweenness_centrality": 0.0002380952380952381, "eigenvector_centrality": 0.27812657478497466, "pagerank": 0.010726883411221801, "clustering_coefficient": 0.8589743589743589}, "id": "Ondrej Brody"}, {"gender": "m", "nationality": "Armenia", "year": 2003.0, "centrality_measures": {"degree_centrality": 0.0, "closeness_centrality": 0.0, "betweenness_centrality": 0.0, "eigenvector_centrality": 5.5724414651128046e-27, "pagerank": 0.0013591987194371152, "clustering_coefficient": 0}, "id": "Tigran Khachatrian"}, {"gender": "f", "nationality": "Germany", "year": 2003.0, "centrality_measures": {"degree_centrality": 0.035555555555555556, "closeness_centrality": 0.036000000000000004, "betweenness_centrality": 0.0, "eigenvector_centrality": 5.173563042593662e-05, "pagerank": 0.00956794035321134, "clustering_coefficient": 1.0}, "id": "Franziska C. Metzger"}, {"gender": "m", "nationality": "Czech Republic", "year": 2003.0, "centrality_measures": {"degree_centrality": 0.057777777777777775, "closeness_centrality": 0.05807407407407408, "betweenness_centrality": 0.00014550264550264547, "eigenvector_centrality": 0.27991980238631176, "pagerank": 0.01053611877380733, "clustering_coefficient": 0.8717948717948718}, "id": "Pavel Tichon"}, {"gender": "m", "nationality": "Portugal", "year": 2003.0, "centrality_measures": {"degree_centrality": 0.0, "closeness_centrality": 0.0, "betweenness_centrality": 0.0, "eigenvector_centrality": 5.5724414651128046e-27, "pagerank": 0.0013591987194371152, "clustering_coefficient": 0}, "id": "Alberto Placido"}, {"gender": "m", "nationality": "Mexico", "year": 2003.0, "centrality_measures": {"degree_centrality": 0.0, "closeness_centrality": 0.0, "betweenness_centrality": 0.0, "eigenvector_centrality": 5.5724414651128046e-27, "pagerank": 0.0013591987194371152, "clustering_coefficient": 0}, "id": "Fernando de la Mora"}, {"gender": "f", "nationality": "Germany", "year": 2003.0, "centrality_measures": {"degree_centrality": 0.0, "closeness_centrality": 0.0, "betweenness_centrality": 0.0, "eigenvector_centrality": 5.5724414651128046e-27, "pagerank": 0.0013591987194371152, "clustering_coefficient": 0}, "id": "Toni Schmale"}, {"gender": "m", "nationality": "Austria", "year": 2003.0, "centrality_measures": {"degree_centrality": 0.0, "closeness_centrality": 0.0, "betweenness_centrality": 0.0, "eigenvector_centrality": 5.5724414651128046e-27, "pagerank": 0.0013591987194371152, "clustering_coefficient": 0}, "id": "Kevin A. Rausch"}, {"gender": "m", "nationality": "Japan", "year": 2003.0, "centrality_measures": {"degree_centrality": 0.0044444444444444444, "closeness_centrality": 0.01234567901234568, "betweenness_centrality": 0.0, "eigenvector_centrality": 2.2390655159327426e-11, "pagerank": 0.0034796457799173017, "clustering_coefficient": 0}, "id": "Hiro Kurata"}, {"gender": "f", "nationality": "Austria", "year": 2003.0, "centrality_measures": {"degree_centrality": 0.0, "closeness_centrality": 0.0, "betweenness_centrality": 0.0, "eigenvector_centrality": 5.5724414651128046e-27, "pagerank": 0.0013591987194371152, "clustering_coefficient": 0}, "id": "Zenita Komad"}, {"gender": "f", "nationality": "Estonia", "year": 2003.0, "centrality_measures": {"degree_centrality": 0.0, "closeness_centrality": 0.0, "betweenness_centrality": 0.0, "eigenvector_centrality": 5.5724414651128046e-27, "pagerank": 0.0013591987194371152, "clustering_coefficient": 0}, "id": "Anu Vahtra"}, {"gender": "m", "nationality": "Germany", "year": 2003.0, "centrality_measures": {"degree_centrality": 0.0, "closeness_centrality": 0.0, "betweenness_centrality": 0.0, "eigenvector_centrality": 5.5724414651128046e-27, "pagerank": 0.0013591987194371152, "clustering_coefficient": 0}, "id": "Sebastian Stumpf"}, {"gender": "m", "nationality": "Mali", "year": 2003.0, "centrality_measures": {"degree_centrality": 0.0044444444444444444, "closeness_centrality": 0.0044444444444444444, "betweenness_centrality": 0.0, "eigenvector_centrality": 4.6745027053776994e-20, "pagerank": 0.00905721082396169, "clustering_coefficient": 0}, "id": "Mohamed Camara"}, {"gender": "m", "nationality": "USA", "year": 2003.0, "centrality_measures": {"degree_centrality": 0.0, "closeness_centrality": 0.0, "betweenness_centrality": 0.0, "eigenvector_centrality": 5.5724414651128046e-27, "pagerank": 0.0013591987194371152, "clustering_coefficient": 0}, "id": "Masood Kamandy"}, {"gender": "m", "nationality": "New Zealand", "year": 2003.0, "centrality_measures": {"degree_centrality": 0.0, "closeness_centrality": 0.0, "betweenness_centrality": 0.0, "eigenvector_centrality": 5.5724414651128046e-27, "pagerank": 0.0013591987194371152, "clustering_coefficient": 0}, "id": "Ryan Chadfield"}, {"gender": "f", "nationality": "Australia", "year": 2003.0, "centrality_measures": {"degree_centrality": 0.008888888888888889, "closeness_centrality": 0.008888888888888889, "betweenness_centrality": 0.0, "eigenvector_centrality": 5.246073533531044e-16, "pagerank": 0.00905721082396169, "clustering_coefficient": 1.0}, "id": "Daniel du Bern"}, {"gender": "m", "nationality": NaN, "year": 2003.0, "centrality_measures": {"degree_centrality": 0.0, "closeness_centrality": 0.0, "betweenness_centrality": 0.0, "eigenvector_centrality": 5.5724414651128046e-27, "pagerank": 0.0013591987194371152, "clustering_coefficient": 0}, "id": "Gregory Sharp"}, {"gender": "f", "nationality": "New Zealand", "year": 2003.0, "centrality_measures": {"degree_centrality": 0.008888888888888889, "closeness_centrality": 0.008888888888888889, "betweenness_centrality": 0.0, "eigenvector_centrality": 5.246073533531044e-16, "pagerank": 0.00905721082396169, "clustering_coefficient": 1.0}, "id": "Marnie Slater"}, {"gender": "m", "nationality": "Nigeria", "year": 2003.0, "centrality_measures": {"degree_centrality": 0.0044444444444444444, "closeness_centrality": 0.0044444444444444444, "betweenness_centrality": 0.0, "eigenvector_centrality": 4.6745027053776994e-20, "pagerank": 0.00905721082396169, "clustering_coefficient": 0}, "id": "Emeka Okereke"}, {"gender": "f", "nationality": "Germany", "year": 2003.0, "centrality_measures": {"degree_centrality": 0.0, "closeness_centrality": 0.0, "betweenness_centrality": 0.0, "eigenvector_centrality": 5.5724414651128046e-27, "pagerank": 0.0013591987194371152, "clustering_coefficient": 0}, "id": "Stefanie Gutheil"}, {"gender": "m", "nationality": "Mexico", "year": 2003.0, "centrality_measures": {"degree_centrality": 0.0, "closeness_centrality": 0.0, "betweenness_centrality": 0.0, "eigenvector_centrality": 5.5724414651128046e-27, "pagerank": 0.0013591987194371152, "clustering_coefficient": 0}, "id": "Rodrigo Hernandez"}, {"gender": "m", "nationality": "Iran", "year": 2003.0, "centrality_measures": {"degree_centrality": 0.0, "closeness_centrality": 0.0, "betweenness_centrality": 0.0, "eigenvector_centrality": 5.5724414651128046e-27, "pagerank": 0.0013591987194371152, "clustering_coefficient": 0}, "id": "Barbad Golshiri"}, {"gender": "m", "nationality": "United Kingdom", "year": 2003.0, "centrality_measures": {"degree_centrality": 0.0, "closeness_centrality": 0.0, "betweenness_centrality": 0.0, "eigenvector_centrality": 5.5724414651128046e-27, "pagerank": 0.0013591987194371152, "clustering_coefficient": 0}, "id": "Adam Thompson"}, {"gender": "f", "nationality": "Denmark", "year": 2003.0, "centrality_measures": {"degree_centrality": 0.0044444444444444444, "closeness_centrality": 0.0044444444444444444, "betweenness_centrality": 0.0, "eigenvector_centrality": 4.6745027053776994e-20, "pagerank": 0.00905721082396169, "clustering_coefficient": 0}, "id": "Ditte Gantriis"}, {"gender": "f", "nationality": NaN, "year": 2003.0, "centrality_measures": {"degree_centrality": 0.0044444444444444444, "closeness_centrality": 0.0044444444444444444, "betweenness_centrality": 0.0, "eigenvector_centrality": 4.6745027053776994e-20, "pagerank": 0.00905721082396169, "clustering_coefficient": 0}, "id": "Birgitte Stovring"}, {"gender": "f", "nationality": "Denmark", "year": 2003.0, "centrality_measures": {"degree_centrality": 0.0044444444444444444, "closeness_centrality": 0.0044444444444444444, "betweenness_centrality": 0.0, "eigenvector_centrality": 4.6745027053776994e-20, "pagerank": 0.00905721082396169, "clustering_coefficient": 0}, "id": "Ida Kvetny"}, {"gender": "m", "nationality": "Lithuania", "year": 2003.0, "centrality_measures": {"degree_centrality": 0.0044444444444444444, "closeness_centrality": 0.0044444444444444444, "betweenness_centrality": 0.0, "eigenvector_centrality": 4.6745027053776994e-20, "pagerank": 0.00905721082396169, "clustering_coefficient": 0}, "id": "Mindaugas Lukosaitis"}, {"gender": "m", "nationality": "Poland", "year": 2003.0, "centrality_measures": {"degree_centrality": 0.0044444444444444444, "closeness_centrality": 0.0044444444444444444, "betweenness_centrality": 0.0, "eigenvector_centrality": 4.6745027053776994e-20, "pagerank": 0.00905721082396169, "clustering_coefficient": 0}, "id": "Karol Radziszewski"}, {"gender": "m", "nationality": "Australia", "year": 2003.0, "centrality_measures": {"degree_centrality": 0.0, "closeness_centrality": 0.0, "betweenness_centrality": 0.0, "eigenvector_centrality": 5.5724414651128046e-27, "pagerank": 0.0013591987194371152, "clustering_coefficient": 0}, "id": "Tim Sharp"}, {"gender": "f", "nationality": "Austria", "year": 2003.0, "centrality_measures": {"degree_centrality": 0.0, "closeness_centrality": 0.0, "betweenness_centrality": 0.0, "eigenvector_centrality": 5.5724414651128046e-27, "pagerank": 0.0013591987194371152, "clustering_coefficient": 0}, "id": "Katherina Olschbaur"}, {"gender": "m", "nationality": "Taiwan", "year": 2003.0, "centrality_measures": {"degree_centrality": 0.0, "closeness_centrality": 0.0, "betweenness_centrality": 0.0, "eigenvector_centrality": 5.5724414651128046e-27, "pagerank": 0.0013591987194371152, "clustering_coefficient": 0}, "id": "Chi-Tsung Wu"}, {"gender": "m", "nationality": "Italy", "year": 2003.0, "centrality_measures": {"degree_centrality": 0.0, "closeness_centrality": 0.0, "betweenness_centrality": 0.0, "eigenvector_centrality": 5.5724414651128046e-27, "pagerank": 0.0013591987194371152, "clustering_coefficient": 0}, "id": "Giovanni Ozzola"}, {"gender": "m", "nationality": "Romania", "year": 2003.0, "centrality_measures": {"degree_centrality": 0.0, "closeness_centrality": 0.0, "betweenness_centrality": 0.0, "eigenvector_centrality": 5.5724414651128046e-27, "pagerank": 0.0013591987194371152, "clustering_coefficient": 0}, "id": "Cristian Pogacean"}, {"gender": "m", "nationality": "Czech Republic", "year": 2003.0, "centrality_measures": {"degree_centrality": 0.05333333333333333, "closeness_centrality": 0.05444444444444444, "betweenness_centrality": 0.0, "eigenvector_centrality": 0.27460817448713837, "pagerank": 0.009576056929916376, "clustering_coefficient": 1.0}, "id": "Jakub Nepras"}, {"gender": "m", "nationality": NaN, "year": 2003.0, "centrality_measures": {"degree_centrality": 0.0, "closeness_centrality": 0.0, "betweenness_centrality": 0.0, "eigenvector_centrality": 5.5724414651128046e-27, "pagerank": 0.0013591987194371152, "clustering_coefficient": 0}, "id": "John Dogg"}, {"gender": "f", "nationality": "Chile", "year": 2003.0, "centrality_measures": {"degree_centrality": 0.0, "closeness_centrality": 0.0, "betweenness_centrality": 0.0, "eigenvector_centrality": 5.5724414651128046e-27, "pagerank": 0.0013591987194371152, "clustering_coefficient": 0}, "id": "Catalina Schliebener"}, {"gender": "m", "nationality": NaN, "year": 2003.0, "centrality_measures": {"degree_centrality": 0.05333333333333333, "closeness_centrality": 0.05444444444444444, "betweenness_centrality": 0.0, "eigenvector_centrality": 0.27460817448713837, "pagerank": 0.009576056929916376, "clustering_coefficient": 1.0}, "id": "David Travnicek"}, {"gender": "m", "nationality": NaN, "year": 2003.0, "centrality_measures": {"degree_centrality": 0.05333333333333333, "closeness_centrality": 0.05444444444444444, "betweenness_centrality": 0.0, "eigenvector_centrality": 0.27460817448713837, "pagerank": 0.009576056929916376, "clustering_coefficient": 1.0}, "id": "Martin Sohajek"}, {"gender": "m", "nationality": "USA", "year": 2003.0, "centrality_measures": {"degree_centrality": 0.017777777777777778, "closeness_centrality": 0.01851851851851852, "betweenness_centrality": 0.0, "eigenvector_centrality": 8.628033669392661e-11, "pagerank": 0.009597373066347566, "clustering_coefficient": 1.0}, "id": "Nick Lowe"}, {"gender": "m", "nationality": "France", "year": 2003.0, "centrality_measures": {"degree_centrality": 0.017777777777777778, "closeness_centrality": 0.017777777777777778, "betweenness_centrality": 0.0, "eigenvector_centrality": 6.64286788119412e-11, "pagerank": 0.00905721082396169, "clustering_coefficient": 1.0}, "id": "Maxime Chanson"}, {"gender": "m", "nationality": "Cuba", "year": 2003.0, "centrality_measures": {"degree_centrality": 0.0, "closeness_centrality": 0.0, "betweenness_centrality": 0.0, "eigenvector_centrality": 5.5724414651128046e-27, "pagerank": 0.0013591987194371152, "clustering_coefficient": 0}, "id": "Miguel Florido"}, {"gender": "m", "nationality": "Germany", "year": 2003.0, "centrality_measures": {"degree_centrality": 0.017777777777777778, "closeness_centrality": 0.01851851851851852, "betweenness_centrality": 0.0, "eigenvector_centrality": 8.628033669392661e-11, "pagerank": 0.009597373066347566, "clustering_coefficient": 1.0}, "id": "Nick Mauss"}, {"gender": "m", "nationality": "Ukraine", "year": 2003.0, "centrality_measures": {"degree_centrality": 0.0, "closeness_centrality": 0.0, "betweenness_centrality": 0.0, "eigenvector_centrality": 5.5724414651128046e-27, "pagerank": 0.0013591987194371152, "clustering_coefficient": 0}, "id": "Ivan Bazak"}, {"gender": "m", "nationality": "Argentina", "year": 2003.0, "centrality_measures": {"degree_centrality": 0.0, "closeness_centrality": 0.0, "betweenness_centrality": 0.0, "eigenvector_centrality": 5.5724414651128046e-27, "pagerank": 0.0013591987194371152, "clustering_coefficient": 0}, "id": "Adri\u00e1n Villar Rojas"}, {"gender": "f", "nationality": "China", "year": 2003.0, "centrality_measures": {"degree_centrality": 0.0044444444444444444, "closeness_centrality": 0.0044444444444444444, "betweenness_centrality": 0.0, "eigenvector_centrality": 4.6745027053776994e-20, "pagerank": 0.00905721082396169, "clustering_coefficient": 0}, "id": "Jie Zhang"}, {"gender": "m", "nationality": "China", "year": 2003.0, "centrality_measures": {"degree_centrality": 0.0044444444444444444, "closeness_centrality": 0.0044444444444444444, "betweenness_centrality": 0.0, "eigenvector_centrality": 4.6745027053776994e-20, "pagerank": 0.00905721082396169, "clustering_coefficient": 0}, "id": "Jianhua Liao"}, {"gender": "m", "nationality": "Kosovo", "year": 2003.0, "centrality_measures": {"degree_centrality": 0.0, "closeness_centrality": 0.0, "betweenness_centrality": 0.0, "eigenvector_centrality": 5.5724414651128046e-27, "pagerank": 0.0013591987194371152, "clustering_coefficient": 0}, "id": "Jakup Ferri"}, {"gender": "f", "nationality": "Finland", "year": 2003.0, "centrality_measures": {"degree_centrality": 0.0, "closeness_centrality": 0.0, "betweenness_centrality": 0.0, "eigenvector_centrality": 5.5724414651128046e-27, "pagerank": 0.0013591987194371152, "clustering_coefficient": 0}, "id": "Pilvi Takala"}, {"gender": "m", "nationality": "USA", "year": 2003.0, "centrality_measures": {"degree_centrality": 0.0, "closeness_centrality": 0.0, "betweenness_centrality": 0.0, "eigenvector_centrality": 5.5724414651128046e-27, "pagerank": 0.0013591987194371152, "clustering_coefficient": 0}, "id": "Patrick Martinez"}, {"gender": "m", "nationality": "Switzerland", "year": 2003.0, "centrality_measures": {"degree_centrality": 0.0, "closeness_centrality": 0.0, "betweenness_centrality": 0.0, "eigenvector_centrality": 5.5724414651128046e-27, "pagerank": 0.0013591987194371152, "clustering_coefficient": 0}, "id": "Denis Savary"}, {"gender": "m", "nationality": "United Kingdom", "year": 2003.0, "centrality_measures": {"degree_centrality": 0.0, "closeness_centrality": 0.0, "betweenness_centrality": 0.0, "eigenvector_centrality": 5.5724414651128046e-27, "pagerank": 0.0013591987194371152, "clustering_coefficient": 0}, "id": "Gary Stevens"}, {"gender": "m", "nationality": "Latvia", "year": 2003.0, "centrality_measures": {"degree_centrality": 0.0044444444444444444, "closeness_centrality": 0.0044444444444444444, "betweenness_centrality": 0.0, "eigenvector_centrality": 4.6745027053776994e-20, "pagerank": 0.00905721082396169, "clustering_coefficient": 0}, "id": "Miks Mitrevics"}], "links": [{"country": "Czech Republic", "source": "Adela Babanova", "target": "Pavla Scerankov\u00e1"}, {"country": "Czech Republic", "source": "Adela Babanova", "target": "Pavla Gajdosikova"}, {"country": "Czech Republic", "source": "Adela Babanova", "target": "Pavel Tichon"}, {"country": "Czech Republic", "source": "Adela Babanova", "target": "Linda Ciharov\u00ef\u00bf\u00bd"}, {"country": "Czech Republic", "source": "Adela Babanova", "target": "Vasil Artamonov"}, {"country": "Czech Republic", "source": "Adela Babanova", "target": "Dominik Lang"}, {"country": "Czech Republic", "source": "Adela Babanova", "target": "Evzen Simera"}, {"country": "Czech Republic", "source": "Adela Babanova", "target": "Adam Stech"}, {"country": "Czech Republic", "source": "Adela Babanova", "target": "Eva Kotatkova"}, {"country": "Czech Republic", "source": "Adela Babanova", "target": "Ondrej Brody"}, {"country": "Czech Republic", "source": "Adela Babanova", "target": "Jakub Nepras"}, {"country": "Czech Republic", "source": "Adela Babanova", "target": "David Travnicek"}, {"country": "Czech Republic", "source": "Adela Babanova", "target": "Martin Sohajek"}, {"country": "Czech Republic", "source": "Linda Ciharov\u00ef\u00bf\u00bd", "target": "Pavla Scerankov\u00e1"}, {"country": "Czech Republic", "source": "Linda Ciharov\u00ef\u00bf\u00bd", "target": "Vasil Artamonov"}, {"country": "Czech Republic", "source": "Linda Ciharov\u00ef\u00bf\u00bd", "target": "Dominik Lang"}, {"country": "Czech Republic", "source": "Linda Ciharov\u00ef\u00bf\u00bd", "target": "Evzen Simera"}, {"country": "Czech Republic", "source": "Linda Ciharov\u00ef\u00bf\u00bd", "target": "Adam Stech"}, {"country": "Czech Republic", "source": "Linda Ciharov\u00ef\u00bf\u00bd", "target": "Eva Kotatkova"}, {"country": "Czech Republic", "source": "Linda Ciharov\u00ef\u00bf\u00bd", "target": "Ondrej Brody"}, {"country": "Czech Republic", "source": "Linda Ciharov\u00ef\u00bf\u00bd", "target": "Pavel Tichon"}, {"country": "Czech Republic", "source": "Linda Ciharov\u00ef\u00bf\u00bd", "target": "Jakub Nepras"}, {"country": "Czech Republic", "source": "Linda Ciharov\u00ef\u00bf\u00bd", "target": "David Travnicek"}, {"country": "Czech Republic", "source": "Linda Ciharov\u00ef\u00bf\u00bd", "target": "Martin Sohajek"}, {"country": "Czech Republic", "source": "Radovan Cerevka", "target": "Ivan Dudas"}, {"country": "Czech Republic", "source": "Radovan Cerevka", "target": "Matej Longauer"}, {"country": "Czech Republic", "source": "Radovan Cerevka", "target": "Tom\u00e1s Makara"}, {"country": "France", "source": "Antoine Roegiers", "target": "Julie Curtiss"}, {"country": "France", "source": "Antoine Roegiers", "target": "Estelle Hanania"}, {"country": "France", "source": "Antoine Roegiers", "target": "Roxane Borujerdi"}, {"country": "France", "source": "Antoine Roegiers", "target": "Maxime Chanson"}, {"country": "Germany", "source": "Sina Heffner", "target": "Gabriel Braun"}, {"country": "Germany", "source": "Sina Heffner", "target": "Lukas Beyeler"}, {"country": "Germany", "source": "Sina Heffner", "target": "Vladimir Logutov"}, {"country": "Germany", "source": "Sina Heffner", "target": "Gordon Castellane"}, {"country": "Germany", "source": "Sina Heffner", "target": "Swantje Hielscher"}, {"country": "Germany", "source": "Sina Heffner", "target": "Guillaume Pilet"}, {"country": "Germany", "source": "Sina Heffner", "target": "Tatiana Arce"}, {"country": "Germany", "source": "Sina Heffner", "target": "Franziska C. Metzger"}, {"country": "Austria", "source": "Ana Hoffner", "target": "Anna Barfuss"}, {"country": "Austria", "source": "Ana Hoffner", "target": "Georg Tiller"}, {"country": "Austria", "source": "Ana Hoffner", "target": "Verena Dengler"}, {"country": "Austria", "source": "Ana Hoffner", "target": "Daniel Domig"}, {"country": "Austria", "source": "Anna Barfuss", "target": "Georg Tiller"}, {"country": "Austria", "source": "Anna Barfuss", "target": "Verena Dengler"}, {"country": "Austria", "source": "Anna Barfuss", "target": "Daniel Domig"}, {"country": "Austria", "source": "Georg Tiller", "target": "Verena Dengler"}, {"country": "Austria", "source": "Georg Tiller", "target": "Daniel Domig"}, {"country": "Austria", "source": "Verena Dengler", "target": "Daniel Domig"}, {"country": "USA", "source": "Wei Jia", "target": "Liang Hao"}, {"country": "Germany", "source": "Gabriel Braun", "target": "Lukas Beyeler"}, {"country": "Germany", "source": "Gabriel Braun", "target": "Vladimir Logutov"}, {"country": "Germany", "source": "Gabriel Braun", "target": "Gordon Castellane"}, {"country": "Germany", "source": "Gabriel Braun", "target": "Swantje Hielscher"}, {"country": "Germany", "source": "Gabriel Braun", "target": "Guillaume Pilet"}, {"country": "Germany", "source": "Gabriel Braun", "target": "Tatiana Arce"}, {"country": "Germany", "source": "Gabriel Braun", "target": "Franziska C. Metzger"}, {"country": "France", "source": "Julie Curtiss", "target": "Estelle Hanania"}, {"country": "France", "source": "Julie Curtiss", "target": "Roxane Borujerdi"}, {"country": "France", "source": "Julie Curtiss", "target": "Maxime Chanson"}, {"country": "Germany", "source": "Lukas Beyeler", "target": "Vladimir Logutov"}, {"country": "Germany", "source": "Lukas Beyeler", "target": "Gordon Castellane"}, {"country": "Germany", "source": "Lukas Beyeler", "target": "Swantje Hielscher"}, {"country": "Germany", "source": "Lukas Beyeler", "target": "Guillaume Pilet"}, {"country": "Germany", "source": "Lukas Beyeler", "target": "Tatiana Arce"}, {"country": "Germany", "source": "Lukas Beyeler", "target": "Franziska C. Metzger"}, {"country": "USA", "source": "Joe Grillo", "target": "Mathew Cerletty"}, {"country": "USA", "source": "Joe Grillo", "target": "Matt Leines"}, {"country": "USA", "source": "Joe Grillo", "target": "Nick Lowe"}, {"country": "USA", "source": "Joe Grillo", "target": "Nick Mauss"}, {"country": "France", "source": "Estelle Hanania", "target": "Roxane Borujerdi"}, {"country": "France", "source": "Estelle Hanania", "target": "Maxime Chanson"}, {"country": "Italy", "source": "Davide Zucco", "target": "Elisa Rossi"}, {"country": "Austria", "source": "Miriam Laussegger", "target": "Christoph Meier"}, {"country": "Austria", "source": "Miriam Laussegger", "target": "Nadim Vardag"}, {"country": "Austria", "source": "Miriam Laussegger", "target": "Tove Storch"}, {"country": "Austria", "source": "Miriam Laussegger", "target": "Katharina Heistinger"}, {"country": "Austria", "source": "Christoph Meier", "target": "Christoph Meier"}, {"country": "Austria", "source": "Christoph Meier", "target": "Nadim Vardag"}, {"country": "Austria", "source": "Christoph Meier", "target": "Tove Storch"}, {"country": "Austria", "source": "Christoph Meier", "target": "Katharina Heistinger"}, {"country": "Poland", "source": "Anna Loskiewicz", "target": "Karol Radziszewski"}, {"country": "Switzerland", "source": "Noemi Grieder", "target": "Tobias Kaspar"}, {"country": "New Zealand", "source": "Amy Howden-Chapman", "target": "Daniel du Bern"}, {"country": "New Zealand", "source": "Amy Howden-Chapman", "target": "Marnie Slater"}, {"country": "Australia", "source": "Christopher LG Hill", "target": "Kate Rohde"}, {"country": "Czech Republic", "source": "Pavla Scerankov\u00e1", "target": "Pavla Gajdosikova"}, {"country": "Czech Republic", "source": "Pavla Scerankov\u00e1", "target": "Pavel Tichon"}, {"country": "Czech Republic", "source": "Pavla Scerankov\u00e1", "target": "Vasil Artamonov"}, {"country": "Czech Republic", "source": "Pavla Scerankov\u00e1", "target": "Dominik Lang"}, {"country": "Czech Republic", "source": "Pavla Scerankov\u00e1", "target": "Evzen Simera"}, {"country": "Czech Republic", "source": "Pavla Scerankov\u00e1", "target": "Adam Stech"}, {"country": "Czech Republic", "source": "Pavla Scerankov\u00e1", "target": "Eva Kotatkova"}, {"country": "Czech Republic", "source": "Pavla Scerankov\u00e1", "target": "Ondrej Brody"}, {"country": "Czech Republic", "source": "Pavla Scerankov\u00e1", "target": "Jakub Nepras"}, {"country": "Czech Republic", "source": "Pavla Scerankov\u00e1", "target": "David Travnicek"}, {"country": "Czech Republic", "source": "Pavla Scerankov\u00e1", "target": "Martin Sohajek"}, {"country": "Czech Republic", "source": "Vasil Artamonov", "target": "Dominik Lang"}, {"country": "Czech Republic", "source": "Vasil Artamonov", "target": "Evzen Simera"}, {"country": "Czech Republic", "source": "Vasil Artamonov", "target": "Adam Stech"}, {"country": "Czech Republic", "source": "Vasil Artamonov", "target": "Eva Kotatkova"}, {"country": "Czech Republic", "source": "Vasil Artamonov", "target": "Ondrej Brody"}, {"country": "Czech Republic", "source": "Vasil Artamonov", "target": "Pavel Tichon"}, {"country": "Czech Republic", "source": "Vasil Artamonov", "target": "Jakub Nepras"}, {"country": "Czech Republic", "source": "Vasil Artamonov", "target": "David Travnicek"}, {"country": "Czech Republic", "source": "Vasil Artamonov", "target": "Martin Sohajek"}, {"country": "Czech Republic", "source": "Dominik Lang", "target": "Evzen Simera"}, {"country": "Czech Republic", "source": "Dominik Lang", "target": "Adam Stech"}, {"country": "Czech Republic", "source": "Dominik Lang", "target": "Eva Kotatkova"}, {"country": "Czech Republic", "source": "Dominik Lang", "target": "Ondrej Brody"}, {"country": "Czech Republic", "source": "Dominik Lang", "target": "Pavel Tichon"}, {"country": "Czech Republic", "source": "Dominik Lang", "target": "Jakub Nepras"}, {"country": "Czech Republic", "source": "Dominik Lang", "target": "David Travnicek"}, {"country": "Czech Republic", "source": "Dominik Lang", "target": "Martin Sohajek"}, {"country": "Austria", "source": "Nadim Vardag", "target": "Tove Storch"}, {"country": "Austria", "source": "Nadim Vardag", "target": "Katharina Heistinger"}, {"country": "Austria", "source": "Tove Storch", "target": "Katharina Heistinger"}, {"country": "China", "source": "Li Shurui", "target": "James Ryan"}, {"country": "Belgium", "source": "Matthieu Ronsse", "target": "Nick Ervinck"}, {"country": "Germany", "source": "Vladimir Logutov", "target": "Gordon Castellane"}, {"country": "Germany", "source": "Vladimir Logutov", "target": "Swantje Hielscher"}, {"country": "Germany", "source": "Vladimir Logutov", "target": "Guillaume Pilet"}, {"country": "Germany", "source": "Vladimir Logutov", "target": "Tatiana Arce"}, {"country": "Germany", "source": "Vladimir Logutov", "target": "Franziska C. Metzger"}, {"country": "Germany", "source": "Vladimir Logutov", "target": "Andrey Syailev"}, {"country": "Denmark", "source": "Ditte Ejlerskov", "target": "Birgitte Stovring"}, {"country": "USA", "source": "Mathew Cerletty", "target": "Matt Leines"}, {"country": "USA", "source": "Mathew Cerletty", "target": "Nick Lowe"}, {"country": "USA", "source": "Mathew Cerletty", "target": "Nick Mauss"}, {"country": "Germany", "source": "Gordon Castellane", "target": "Swantje Hielscher"}, {"country": "Germany", "source": "Gordon Castellane", "target": "Guillaume Pilet"}, {"country": "Germany", "source": "Gordon Castellane", "target": "Tatiana Arce"}, {"country": "Germany", "source": "Gordon Castellane", "target": "Franziska C. Metzger"}, {"country": "Germany", "source": "Swantje Hielscher", "target": "Guillaume Pilet"}, {"country": "Germany", "source": "Swantje Hielscher", "target": "Tatiana Arce"}, {"country": "Germany", "source": "Swantje Hielscher", "target": "Franziska C. Metzger"}, {"country": "Germany", "source": "Guillaume Pilet", "target": "Tatiana Arce"}, {"country": "Germany", "source": "Guillaume Pilet", "target": "Franziska C. Metzger"}, {"country": "Austria", "source": "Simon Mullan", "target": "Michael Niemetz"}, {"country": "France", "source": "Roxane Borujerdi", "target": "Maxime Chanson"}, {"country": "USA", "source": "Matt Leines", "target": "Nick Lowe"}, {"country": "USA", "source": "Matt Leines", "target": "Nick Mauss"}, {"country": "USA", "source": "Matt Leines", "target": "Hiro Kurata"}, {"country": "Germany", "source": "Manuela Gernedel", "target": "Anna Witt"}, {"country": "Germany", "source": "Manuela Gernedel", "target": "Lisa Erb"}, {"country": "Germany", "source": "Anna Witt", "target": "Lisa Erb"}, {"country": "Germany", "source": "Tatiana Arce", "target": "Franziska C. Metzger"}, {"country": "Czech Republic", "source": "Evzen Simera", "target": "Adam Stech"}, {"country": "Czech Republic", "source": "Evzen Simera", "target": "Eva Kotatkova"}, {"country": "Czech Republic", "source": "Evzen Simera", "target": "Ondrej Brody"}, {"country": "Czech Republic", "source": "Evzen Simera", "target": "Pavel Tichon"}, {"country": "Czech Republic", "source": "Evzen Simera", "target": "Jakub Nepras"}, {"country": "Czech Republic", "source": "Evzen Simera", "target": "David Travnicek"}, {"country": "Czech Republic", "source": "Evzen Simera", "target": "Martin Sohajek"}, {"country": "Czech Republic", "source": "Evzen Simera", "target": "Vladim\u00edr V\u00e9la"}, {"country": "Czech Republic", "source": "Adam Stech", "target": "Eva Kotatkova"}, {"country": "Czech Republic", "source": "Adam Stech", "target": "Ondrej Brody"}, {"country": "Czech Republic", "source": "Adam Stech", "target": "Pavel Tichon"}, {"country": "Czech Republic", "source": "Adam Stech", "target": "Jakub Nepras"}, {"country": "Czech Republic", "source": "Adam Stech", "target": "David Travnicek"}, {"country": "Czech Republic", "source": "Adam Stech", "target": "Martin Sohajek"}, {"country": "Czech Republic", "source": "Pavla Gajdosikova", "target": "Pavel Tichon"}, {"country": "Czech Republic", "source": "Ivan Dudas", "target": "Matej Longauer"}, {"country": "Czech Republic", "source": "Ivan Dudas", "target": "Tom\u00e1s Makara"}, {"country": "Czech Republic", "source": "Vladim\u00edr V\u00e9la", "target": "Ondrej Brody"}, {"country": "Czech Republic", "source": "Matej Longauer", "target": "Tom\u00e1s Makara"}, {"country": "Slovakia", "source": "Lukas Schneider", "target": "Andrea Junekov\u00e1"}, {"country": "Slovakia", "source": "Lukas Schneider", "target": "Juraj Anusev"}, {"country": "Slovakia", "source": "Andrea Junekov\u00e1", "target": "Juraj Anusev"}, {"country": "China", "source": "Yan Lei", "target": "I\u00f1aki Bonillas"}, {"country": "Czech Republic", "source": "Eva Kotatkova", "target": "Ondrej Brody"}, {"country": "Czech Republic", "source": "Eva Kotatkova", "target": "Pavel Tichon"}, {"country": "Czech Republic", "source": "Eva Kotatkova", "target": "Jakub Nepras"}, {"country": "Czech Republic", "source": "Eva Kotatkova", "target": "David Travnicek"}, {"country": "Czech Republic", "source": "Eva Kotatkova", "target": "Martin Sohajek"}, {"country": "Austria", "source": "Iris Nemecek", "target": "Alfredo Barsuglia"}, {"country": "Austria", "source": "Iris Nemecek", "target": "Robert Muntean"}, {"country": "Austria", "source": "Alfredo Barsuglia", "target": "Robert Muntean"}, {"country": "Germany", "source": "Ondrej Brody", "target": "Pavel Tichon"}, {"country": "Germany", "source": "Ondrej Brody", "target": "Jakub Nepras"}, {"country": "Germany", "source": "Ondrej Brody", "target": "David Travnicek"}, {"country": "Germany", "source": "Ondrej Brody", "target": "Martin Sohajek"}, {"country": "Czech Republic", "source": "Pavel Tichon", "target": "Jakub Nepras"}, {"country": "Czech Republic", "source": "Pavel Tichon", "target": "David Travnicek"}, {"country": "Czech Republic", "source": "Pavel Tichon", "target": "Martin Sohajek"}, {"country": "Mali", "source": "Mohamed Camara", "target": "Emeka Okereke"}, {"country": "New Zealand", "source": "Daniel du Bern", "target": "Marnie Slater"}, {"country": "Denmark", "source": "Ditte Gantriis", "target": "Ida Kvetny"}, {"country": "Lithuania", "source": "Mindaugas Lukosaitis", "target": "Miks Mitrevics"}, {"country": "Czech Republic", "source": "Jakub Nepras", "target": "David Travnicek"}, {"country": "Czech Republic", "source": "Jakub Nepras", "target": "Martin Sohajek"}, {"country": "Czech Republic", "source": "David Travnicek", "target": "Martin Sohajek"}, {"country": "Australia", "source": "Nick Lowe", "target": "Nick Mauss"}, {"country": "China", "source": "Jie Zhang", "target": "Jianhua Liao"}], "year": 2003.0}